{"1410105005": {"n": 796, "uf": 2135.0, "ufm2": 39.38, "plus": 35.9, "plus_tipo": "Departamento", "n_ini": 345, "n_fin": 62}, "1410108002": {"n": 208, "uf": 2751.0, "ufm2": 32.05, "plus": 24.3, "plus_tipo": "Casa", "n_ini": 70, "n_fin": 45}, "1410108003": {"n": 372, "uf": 3273.0, "ufm2": 32.82, "plus": 36.9, "plus_tipo": "Casa", "n_ini": 121, "n_fin": 86}, "1410106004": {"n": 306, "uf": 1210.0, "ufm2": 20.48, "plus": 34.0, "plus_tipo": "Casa", "n_ini": 96, "n_fin": 58}, "1410108008": {"n": 258, "uf": 836.0, "ufm2": 18.62, "plus": 2.5, "plus_tipo": "Casa", "n_ini": 57, "n_fin": 55}, "1410108004": {"n": 250, "uf": 849.0, "ufm2": 18.3, "plus": 86.7, "plus_tipo": "Casa", "n_ini": 82, "n_fin": 55}, "1410117002": {"n": 66, "uf": 590.0, "ufm2": 11.04, "plus": -13.9, "plus_tipo": "Casa", "n_ini": 14, "n_fin": 16}, "1410107006": {"n": 473, "uf": 1508.0, "ufm2": 30.78, "plus": 60.0, "plus_tipo": "Casa", "n_ini": 188, "n_fin": 87}, "1410110001": {"n": 257, "uf": 2748.0, "ufm2": 65.34, "plus": 24.6, "plus_tipo": "Departamento", "n_ini": 13, "n_fin": 134}, "1410101001": {"n": 230, "uf": 2845.0, "ufm2": 41.04, "plus": -19.5, "plus_tipo": "Casa", "n_ini": 30, "n_fin": 27}, "1410109002": {"n": 447, "uf": 2655.0, "ufm2": 39.69, "plus": 85.8, "plus_tipo": "Departamento", "n_ini": 89, "n_fin": 51}, "1410110003": {"n": 142, "uf": 1660.0, "ufm2": 17.43, "plus": -11.4, "plus_tipo": "Casa", "n_ini": 55, "n_fin": 33}, "1410107001": {"n": 289, "uf": 1466.0, "ufm2": 18.66, "plus": -0.2, "plus_tipo": "Casa", "n_ini": 64, "n_fin": 55}, "1410108005": {"n": 316, "uf": 2095.0, "ufm2": 35.85, "plus": 13.4, "plus_tipo": "Casa", "n_ini": 56, "n_fin": 23}, "1410104001": {"n": 322, "uf": 1100.0, "ufm2": 21.16, "plus": -10.9, "plus_tipo": "Casa", "n_ini": 65, "n_fin": 39}, "1410108006": {"n": 301, "uf": 817.0, "ufm2": 18.8, "plus": 1.8, "plus_tipo": "Casa", "n_ini": 94, "n_fin": 65}, "1410107002": {"n": 186, "uf": 1036.0, "ufm2": 17.08, "plus": 3.0, "plus_tipo": "Casa", "n_ini": 47, "n_fin": 50}, "1410108007": {"n": 195, "uf": 830.0, "ufm2": 17.8, "plus": 101.5, "plus_tipo": "Casa", "n_ini": 61, "n_fin": 43}, "1410105002": {"n": 155, "uf": 648.0, "ufm2": 11.47, "plus": -15.4, "plus_tipo": "Casa", "n_ini": 38, "n_fin": 41}, "1410106006": {"n": 41, "uf": 961.0, "ufm2": 15.58, "plus": 124.7, "plus_tipo": "Casa", "n_ini": 10, "n_fin": 12}, "1410106003": {"n": 226, "uf": 960.0, "ufm2": 15.85, "plus": 6.9, "plus_tipo": "Casa", "n_ini": 61, "n_fin": 49}, "1410109001": {"n": 151, "uf": 1914.0, "ufm2": 16.59, "plus": 0.1, "plus_tipo": "Casa", "n_ini": 28, "n_fin": 23}, "1410108010": {"n": 1717, "uf": 1341.0, "ufm2": 25.0, "plus": -17.5, "plus_tipo": "Casa", "n_ini": 512, "n_fin": 562}, "1410107005": {"n": 817, "uf": 2040.0, "ufm2": 28.89, "plus": 17.4, "plus_tipo": "Casa", "n_ini": 134, "n_fin": 83}, "1410105003": {"n": 168, "uf": 980.0, "ufm2": 15.89, "plus": 2.1, "plus_tipo": "Casa", "n_ini": 41, "n_fin": 34}, "1410106002": {"n": 109, "uf": 969.0, "ufm2": 17.41, "plus": 7.7, "plus_tipo": "Casa", "n_ini": 24, "n_fin": 31}, "1410105001": {"n": 732, "uf": 2045.0, "ufm2": 29.71, "plus": 55.8, "plus_tipo": "Casa", "n_ini": 75, "n_fin": 74}, "1410104003": {"n": 207, "uf": 1987.0, "ufm2": 31.48, "plus": 16.1, "plus_tipo": "Casa", "n_ini": 56, "n_fin": 44}, "1410104005": {"n": 948, "uf": 1832.0, "ufm2": 33.31, "plus": 74.1, "plus_tipo": "Casa", "n_ini": 384, "n_fin": 111}, "1410117001": {"n": 195, "uf": 1065.0, "ufm2": 15.85, "plus": 13.8, "plus_tipo": "Casa", "n_ini": 58, "n_fin": 40}, "1410116001": {"n": 456, "uf": 5674.0, "ufm2": 48.91, "plus": 48.2, "plus_tipo": "Departamento", "n_ini": 87, "n_fin": 30}, "1410105004": {"n": 95, "uf": 2343.0, "ufm2": 28.38, "plus": -8.1, "plus_tipo": "Casa", "n_ini": 22, "n_fin": 16}, "1410103001": {"n": 545, "uf": 3246.0, "ufm2": 72.8, "plus": 128.4, "plus_tipo": "Departamento", "n_ini": 34, "n_fin": 156}, "1410108011": {"n": 290, "uf": 1362.0, "ufm2": 25.68, "plus": 15.9, "plus_tipo": "Casa", "n_ini": 20, "n_fin": 53}, "1410110002": {"n": 168, "uf": 1940.0, "ufm2": 19.01, "plus": 27.4, "plus_tipo": "Casa", "n_ini": 48, "n_fin": 35}, "1410108001": {"n": 569, "uf": 3362.0, "ufm2": 40.07, "plus": 20.6, "plus_tipo": "Casa", "n_ini": 115, "n_fin": 92}, "1410106001": {"n": 407, "uf": 1017.0, "ufm2": 17.57, "plus": 183.7, "plus_tipo": "Casa", "n_ini": 133, "n_fin": 77}, "1410107003": {"n": 565, "uf": 1528.0, "ufm2": 27.77, "plus": 15.9, "plus_tipo": "Casa", "n_ini": 74, "n_fin": 51}, "1410106005": {"n": 172, "uf": 886.0, "ufm2": 14.53, "plus": 0.1, "plus_tipo": "Casa", "n_ini": 51, "n_fin": 33}, "1410102001": {"n": 1506, "uf": 3653.0, "ufm2": 62.16, "plus": 71.6, "plus_tipo": "Departamento", "n_ini": 121, "n_fin": 416}, "1410104004": {"n": 198, "uf": 719.0, "ufm2": 16.13, "plus": 8.5, "plus_tipo": "Casa", "n_ini": 57, "n_fin": 47}, "1410108009": {"n": 293, "uf": 1850.0, "ufm2": 32.45, "plus": 10.5, "plus_tipo": "Casa", "n_ini": 90, "n_fin": 68}, "1410107004": {"n": 94, "uf": 995.0, "ufm2": 17.32, "plus": 119.1, "plus_tipo": "Casa", "n_ini": 29, "n_fin": 26}, "1410104002": {"n": 46, "uf": 1297.0, "ufm2": 20.94, "plus": 5.6, "plus_tipo": "Casa", "n_ini": 11, "n_fin": 13}}