{"410601001": {"n": 429, "uf": 1160.0, "ufm2": 27.4, "plus": 6.5, "plus_tipo": "Casa", "n_ini": 86, "n_fin": 56}, "410602002": {"n": 264, "uf": 805.0, "ufm2": 14.24, "plus": 20.9, "plus_tipo": "Casa", "n_ini": 66, "n_fin": 65}, "410601002": {"n": 112, "uf": 939.0, "ufm2": 16.6, "plus": 66.1, "plus_tipo": "Casa", "n_ini": 21, "n_fin": 31}, "410602001": {"n": 243, "uf": 618.0, "ufm2": 14.74, "plus": 47.3, "plus_tipo": "Casa", "n_ini": 90, "n_fin": 45}, "410603001": {"n": 100, "uf": 502.0, "ufm2": 11.49, "plus": -17.3, "plus_tipo": "Casa", "n_ini": 32, "n_fin": 24}}