{"meta": {"fuente": "Catastro SII enriquecido (anio_construccion) + Censo 2017/2024", "area": "San Antonio", "comunas_con_sii": 1, "criterio_casa_depto": "Departamento = predio habitacional pisos_max>=3; Casa = 1-2 pisos", "m2_sin_anio_excluido": 0}, "ej1_personas_vs_m2": {"pob_2017": 91350, "pob_2024": 96770, "m2_2017": 3142607, "m2_2024": 3778117, "crec_pob_pct": 5.9, "crec_m2_pct": 20.2, "stock_m2_por_anio": {"anios": [2000, 2001, 2002, 2003, 2004, 2005, 2006, 2007, 2008, 2009, 2010, 2011, 2012, 2013, 2014, 2015, 2016, 2017, 2018, 2019, 2020, 2021, 2022, 2023, 2024, 2025], "stock": [1269052, 1392055, 1513380, 1630632, 1739736, 1788047, 1844975, 1991691, 2090078, 2260896, 2307440, 2344602, 2437200, 2679933, 2728755, 2774048, 2834704, 3142607, 3208123, 3304851, 3343421, 3509493, 3570603, 3744651, 3778117, 3778117]}}, "ej5_casa_depto": [{"anio": 2015, "casas": 199, "deptos": 1, "ratio_casa_depto": 199.0}, {"anio": 2016, "casas": 597, "deptos": 72, "ratio_casa_depto": 8.29}, {"anio": 2017, "casas": 323, "deptos": 346, "ratio_casa_depto": 0.93}, {"anio": 2018, "casas": 275, "deptos": 1, "ratio_casa_depto": 275.0}, {"anio": 2019, "casas": 301, "deptos": 561, "ratio_casa_depto": 0.54}, {"anio": 2020, "casas": 73, "deptos": 205, "ratio_casa_depto": 0.36}, {"anio": 2021, "casas": 281, "deptos": 241, "ratio_casa_depto": 1.17}, {"anio": 2022, "casas": 60, "deptos": 214, "ratio_casa_depto": 0.28}, {"anio": 2023, "casas": 77, "deptos": 84, "ratio_casa_depto": 0.92}, {"anio": 2024, "casas": 87, "deptos": 0, "ratio_casa_depto": null}], "ej6_expansion_densidad": [{"anio": 2016, "densificacion": 38203, "expansion": 22453, "pct_densif": 63.0, "ratio_dens_exp": 1.7}, {"anio": 2017, "densificacion": 252336, "expansion": 55567, "pct_densif": 82.0, "ratio_dens_exp": 4.54}, {"anio": 2018, "densificacion": 58371, "expansion": 7145, "pct_densif": 89.1, "ratio_dens_exp": 8.17}, {"anio": 2019, "densificacion": 54773, "expansion": 41955, "pct_densif": 56.6, "ratio_dens_exp": 1.31}, {"anio": 2020, "densificacion": 27609, "expansion": 10961, "pct_densif": 71.6, "ratio_dens_exp": 2.52}, {"anio": 2021, "densificacion": 143776, "expansion": 22296, "pct_densif": 86.6, "ratio_dens_exp": 6.45}, {"anio": 2022, "densificacion": 47209, "expansion": 13901, "pct_densif": 77.3, "ratio_dens_exp": 3.4}, {"anio": 2023, "densificacion": 167157, "expansion": 6891, "pct_densif": 96.0, "ratio_dens_exp": 24.26}, {"anio": 2024, "densificacion": 33119, "expansion": 347, "pct_densif": 99.0, "ratio_dens_exp": 95.44}, {"anio": 2025, "densificacion": 0, "expansion": 0, "pct_densif": null, "ratio_dens_exp": null}], "ej6_totales": {"densificacion": 822553, "expansion": 181516, "pct_densif": 81.9}, "ej4_tipologia_comuna": [{"comuna": "San Antonio", "densif": 822553, "expansion": 181516, "pct_densif": 81.9, "tipologia": "Densificación"}]}