{"cut": "10306", "comuna": "SAN JUAN DE LA COSTA", "region": "LOS LAGOS", "metro": null, "fuente_demografia": "INE base 2017 (comunal) re-anclada al techo nacional INE base 2024 + Censo 2024", "nota": "Demografía: proyección comunal INE base 2017 corregida al techo nacional INE base 2024 (re-anclada al Censo 2024).", "demografia": {"2024": {"pob": 7776, "hogares": 3340, "viviendas": 6794}, "2030": {"tend": {"pob": 7465, "hogares": 3342, "viviendas": 6798}, "alto": {"pob": 7572, "hogares": 3390, "viviendas": 6895}, "bajo": {"pob": 7359, "hogares": 3294, "viviendas": 6701}}, "2035": {"tend": {"pob": 7172, "hogares": 3260, "viviendas": 6632}, "alto": {"pob": 7301, "hogares": 3318, "viviendas": 6750}, "bajo": {"pob": 7044, "hogares": 3202, "viviendas": 6513}}}, "suelo": {"Habitacional": {"2024": 76186, "2030": {"tend": 76231, "alto": 77319, "cons": 76186}, "2035": {"tend": 76186, "alto": 76186, "cons": 76186}}, "Comercio": {"2024": 1501, "2030": {"tend": 1856, "alto": 1962, "cons": 1749}, "2035": {"tend": 2152, "alto": 2347, "cons": 1956}}, "Educacion": {"2024": 8849, "2030": {"tend": 12212, "alto": 13221, "cons": 11203}, "2035": {"tend": 15014, "alto": 16863, "cons": 13165}}, "Salud": {"2024": 4541, "2030": {"tend": 5566, "alto": 5873, "cons": 5258}, "2035": {"tend": 6419, "alto": 6983, "cons": 5856}}, "Oficina": {"2024": 889, "2030": {"tend": 1206, "alto": 1302, "cons": 1111}, "2035": {"tend": 1471, "alto": 1645, "cons": 1296}}, "Industria": {"2024": 0, "2030": {"tend": 0, "alto": 0, "cons": 0}, "2035": {"tend": 0, "alto": 0, "cons": 0}}}}