{"cut": "1107", "comuna": "ALTO HOSPICIO", "region": "TARAPACÁ", "metro": "Iquique-Alto Hospicio", "fuente_demografia": "INE base 2017 (comunal) re-anclada al techo nacional INE base 2024 + Censo 2024", "nota": "Demografía: proyección comunal INE base 2017 corregida al techo nacional INE base 2024 (re-anclada al Censo 2024).", "demografia": {"2024": {"pob": 142086, "hogares": 42150, "viviendas": 46558}, "2030": {"tend": {"pob": 160274, "hogares": 49606, "viviendas": 54794}, "alto": {"pob": 162564, "hogares": 50315, "viviendas": 55577}, "bajo": {"pob": 157984, "hogares": 48898, "viviendas": 54011}}, "2035": {"tend": {"pob": 174723, "hogares": 56012, "viviendas": 61869}, "alto": {"pob": 177851, "hogares": 57014, "viviendas": 62977}, "bajo": {"pob": 171595, "hogares": 55009, "viviendas": 60762}}}, "suelo": {"Habitacional": {"2024": 1662868, "2030": {"tend": 1957025, "alto": 1984991, "cons": 1929059}, "2035": {"tend": 2209716, "alto": 2249290, "cons": 2170179}}, "Comercio": {"2024": 171175, "2030": {"tend": 248269, "alto": 271398, "cons": 225141}, "2035": {"tend": 312515, "alto": 354917, "cons": 270113}}, "Educacion": {"2024": 125349, "2030": {"tend": 144748, "alto": 150567, "cons": 138928}, "2035": {"tend": 160914, "alto": 171583, "cons": 150244}}, "Salud": {"2024": 55995, "2030": {"tend": 60526, "alto": 61885, "cons": 59167}, "2035": {"tend": 64302, "alto": 66793, "cons": 61810}}, "Oficina": {"2024": 12419, "2030": {"tend": 16081, "alto": 17179, "cons": 14982}, "2035": {"tend": 19132, "alto": 21145, "cons": 17118}}, "Industria": {"2024": 87013, "2030": {"tend": 115104, "alto": 123531, "cons": 106677}, "2035": {"tend": 138513, "alto": 153963, "cons": 123063}}}}