{"cut": "13302", "comuna": "LAMPA", "region": "METROPOLITANA DE SANTIAGO", "metro": null, "fuente_demografia": "INE base 2017 (comunal) re-anclada al techo nacional INE base 2024 + Censo 2024", "nota": "Demografía: proyección comunal INE base 2017 corregida al techo nacional INE base 2024 (re-anclada al Censo 2024).", "demografia": {"2024": {"pob": 145160, "hogares": 45445, "viviendas": 50270}, "2030": {"tend": {"pob": 164375, "hogares": 53746, "viviendas": 59453}, "alto": {"pob": 166724, "hogares": 54514, "viviendas": 60302}, "bajo": {"pob": 162027, "hogares": 52979, "viviendas": 58603}}, "2035": {"tend": {"pob": 174441, "hogares": 59077, "viviendas": 65349}, "alto": {"pob": 177564, "hogares": 60134, "viviendas": 66519}, "bajo": {"pob": 171318, "hogares": 58019, "viviendas": 64179}}}, "suelo": {"Habitacional": {"2024": 2859571, "2030": {"tend": 3381939, "alto": 3430233, "cons": 3333587}, "2035": {"tend": 3717328, "alto": 3783883, "cons": 3650774}}, "Comercio": {"2024": 292768, "2030": {"tend": 324836, "alto": 334457, "cons": 315216}, "2035": {"tend": 351560, "alto": 369198, "cons": 333922}}, "Educacion": {"2024": 111356, "2030": {"tend": 142905, "alto": 152370, "cons": 133440}, "2035": {"tend": 169197, "alto": 186549, "cons": 151844}}, "Salud": {"2024": 5840, "2030": {"tend": 6105, "alto": 6185, "cons": 6026}, "2035": {"tend": 6326, "alto": 6472, "cons": 6180}}, "Oficina": {"2024": 10073, "2030": {"tend": 11429, "alto": 11836, "cons": 11022}, "2035": {"tend": 12559, "alto": 13304, "cons": 11813}}, "Industria": {"2024": 1774581, "2030": {"tend": 2232689, "alto": 2370122, "cons": 2095257}, "2035": {"tend": 2614446, "alto": 2866406, "cons": 2362487}}}}