{"cut": "6203", "comuna": "LITUECHE", "region": "LIBERTADOR GENERAL BERNARDO O'HIGGINS", "metro": null, "fuente_demografia": "INE base 2017 (comunal) re-anclada al techo nacional INE base 2024 + Censo 2024", "nota": "Demografía: proyección comunal INE base 2017 corregida al techo nacional INE base 2024 (re-anclada al Censo 2024).", "demografia": {"2024": {"pob": 8852, "hogares": 3408, "viviendas": 5459}, "2030": {"tend": {"pob": 9105, "hogares": 3653, "viviendas": 5851}, "alto": {"pob": 9235, "hogares": 3705, "viviendas": 5934}, "bajo": {"pob": 8975, "hogares": 3600, "viviendas": 5767}}, "2035": {"tend": {"pob": 9176, "hogares": 3813, "viviendas": 6107}, "alto": {"pob": 9340, "hogares": 3881, "viviendas": 6217}, "bajo": {"pob": 9012, "hogares": 3745, "viviendas": 5998}}}, "suelo": {"Habitacional": {"2024": 176561, "2030": {"tend": 189239, "alto": 191924, "cons": 186522}, "2035": {"tend": 197519, "alto": 201077, "cons": 193993}}, "Comercio": {"2024": 26572, "2030": {"tend": 32611, "alto": 34423, "cons": 30800}, "2035": {"tend": 37644, "alto": 40965, "cons": 34322}}, "Educacion": {"2024": 10514, "2030": {"tend": 11141, "alto": 11329, "cons": 10953}, "2035": {"tend": 11663, "alto": 12007, "cons": 11318}}, "Salud": {"2024": 1391, "2030": {"tend": 1391, "alto": 1391, "cons": 1391}, "2035": {"tend": 1391, "alto": 1391, "cons": 1391}}, "Oficina": {"2024": 1858, "2030": {"tend": 1900, "alto": 1912, "cons": 1887}, "2035": {"tend": 1935, "alto": 1958, "cons": 1912}}, "Industria": {"2024": 17192, "2030": {"tend": 17545, "alto": 17651, "cons": 17439}, "2035": {"tend": 17839, "alto": 18034, "cons": 17645}}}}