{"cut": "6304", "comuna": "LOLOL", "region": "LIBERTADOR GENERAL BERNARDO O'HIGGINS", "metro": null, "fuente_demografia": "INE base 2017 (comunal) re-anclada al techo nacional INE base 2024 + Censo 2024", "nota": "Demografía: proyección comunal INE base 2017 corregida al techo nacional INE base 2024 (re-anclada al Censo 2024).", "demografia": {"2024": {"pob": 7791, "hogares": 2897, "viviendas": 3718}, "2030": {"tend": {"pob": 7965, "hogares": 3088, "viviendas": 3963}, "alto": {"pob": 8078, "hogares": 3132, "viviendas": 4020}, "bajo": {"pob": 7851, "hogares": 3044, "viviendas": 3907}}, "2035": {"tend": {"pob": 7993, "hogares": 3210, "viviendas": 4120}, "alto": {"pob": 8136, "hogares": 3267, "viviendas": 4193}, "bajo": {"pob": 7850, "hogares": 3152, "viviendas": 4046}}}, "suelo": {"Habitacional": {"2024": 139153, "2030": {"tend": 148323, "alto": 150456, "cons": 146227}, "2035": {"tend": 154199, "alto": 156931, "cons": 151429}}, "Comercio": {"2024": 11331, "2030": {"tend": 13671, "alto": 14374, "cons": 12969}, "2035": {"tend": 15622, "alto": 16909, "cons": 14335}}, "Educacion": {"2024": 7573, "2030": {"tend": 10283, "alto": 11096, "cons": 9470}, "2035": {"tend": 12541, "alto": 14032, "cons": 11051}}, "Salud": {"2024": 1344, "2030": {"tend": 1344, "alto": 1344, "cons": 1344}, "2035": {"tend": 1344, "alto": 1344, "cons": 1344}}, "Oficina": {"2024": 903, "2030": {"tend": 2034, "alto": 2374, "cons": 1695}, "2035": {"tend": 2977, "alto": 3599, "cons": 2355}}, "Industria": {"2024": 15063, "2030": {"tend": 15084, "alto": 15090, "cons": 15078}, "2035": {"tend": 15102, "alto": 15113, "cons": 15090}}}}