{"cut": "7403", "comuna": "LONGAVÍ", "region": "MAULE", "metro": null, "fuente_demografia": "INE base 2017 (comunal) re-anclada al techo nacional INE base 2024 + Censo 2024", "nota": "Demografía: proyección comunal INE base 2017 corregida al techo nacional INE base 2024 (re-anclada al Censo 2024).", "demografia": {"2024": {"pob": 33299, "hogares": 11995, "viviendas": 14131}, "2030": {"tend": {"pob": 34296, "hogares": 12868, "viviendas": 15159}, "alto": {"pob": 34786, "hogares": 13052, "viviendas": 15376}, "bajo": {"pob": 33806, "hogares": 12684, "viviendas": 14943}}, "2035": {"tend": {"pob": 34665, "hogares": 13471, "viviendas": 15870}, "alto": {"pob": 35286, "hogares": 13712, "viviendas": 16154}, "bajo": {"pob": 34044, "hogares": 13230, "viviendas": 15586}}}, "suelo": {"Habitacional": {"2024": 349492, "2030": {"tend": 374917, "alto": 380284, "cons": 369575}, "2035": {"tend": 392502, "alto": 399525, "cons": 385478}}, "Comercio": {"2024": 35467, "2030": {"tend": 47529, "alto": 51147, "cons": 43910}, "2035": {"tend": 57580, "alto": 64214, "cons": 50946}}, "Educacion": {"2024": 24261, "2030": {"tend": 28180, "alto": 29356, "cons": 27004}, "2035": {"tend": 31446, "alto": 33602, "cons": 29291}}, "Salud": {"2024": 3110, "2030": {"tend": 3110, "alto": 3110, "cons": 3110}, "2035": {"tend": 3110, "alto": 3110, "cons": 3110}}, "Oficina": {"2024": 1779, "2030": {"tend": 1779, "alto": 1779, "cons": 1779}, "2035": {"tend": 1779, "alto": 1779, "cons": 1779}}, "Industria": {"2024": 50601, "2030": {"tend": 77838, "alto": 86009, "cons": 69667}, "2035": {"tend": 100536, "alto": 115517, "cons": 85555}}}}