{"cut": "9104", "comuna": "CURARREHUE", "region": "LA ARAUCANÍA", "metro": null, "fuente_demografia": "INE base 2017 (comunal) re-anclada al techo nacional INE base 2024 + Censo 2024", "nota": "Demografía: proyección comunal INE base 2017 corregida al techo nacional INE base 2024 (re-anclada al Censo 2024).", "demografia": {"2024": {"pob": 7733, "hogares": 2906, "viviendas": 4431}, "2030": {"tend": {"pob": 7743, "hogares": 3036, "viviendas": 4630}, "alto": {"pob": 7854, "hogares": 3080, "viviendas": 4696}, "bajo": {"pob": 7633, "hogares": 2993, "viviendas": 4564}}, "2035": {"tend": {"pob": 7613, "hogares": 3092, "viviendas": 4714}, "alto": {"pob": 7749, "hogares": 3147, "viviendas": 4799}, "bajo": {"pob": 7476, "hogares": 3036, "viviendas": 4630}}}, "suelo": {"Habitacional": {"2024": 56107, "2030": {"tend": 58627, "alto": 59463, "cons": 57791}, "2035": {"tend": 59690, "alto": 60767, "cons": 58627}}, "Comercio": {"2024": 9555, "2030": {"tend": 10922, "alto": 11332, "cons": 10512}, "2035": {"tend": 12062, "alto": 12814, "cons": 11309}}, "Educacion": {"2024": 12423, "2030": {"tend": 12696, "alto": 12778, "cons": 12614}, "2035": {"tend": 12924, "alto": 13074, "cons": 12773}}, "Salud": {"2024": 686, "2030": {"tend": 734, "alto": 748, "cons": 719}, "2035": {"tend": 774, "alto": 800, "cons": 747}}, "Oficina": {"2024": 1901, "2030": {"tend": 2068, "alto": 2118, "cons": 2018}, "2035": {"tend": 2207, "alto": 2298, "cons": 2115}}, "Industria": {"2024": 0, "2030": {"tend": 0, "alto": 0, "cons": 0}, "2035": {"tend": 0, "alto": 0, "cons": 0}}}}