{"anios": [2002, 2003, 2004, 2005, 2006, 2007, 2008, 2009, 2010, 2011, 2012, 2013, 2014, 2015, 2016, 2017, 2018, 2019, 2020, 2021, 2022, 2023, 2024, 2025, 2026, 2027, 2028, 2029, 2030, 2031, 2032, 2033, 2034, 2035], "ciudades": [{"id": "chillan_chillan_viejo", "slug": "chillan_chillan_viejo", "nombre": "Chillán-Chillán Viejo", "es_area": true, "peak_anio": 2035, "aun_creciente": true, "idx65_2024": 83.1, "idx65_2035": 136.7, "mapa_zonal": true}, {"id": "gran_concepcion", "slug": "gran_concepcion", "nombre": "Gran Concepción", "es_area": true, "peak_anio": 2034, "aun_creciente": false, "idx65_2024": 85.2, "idx65_2035": 141.0, "mapa_zonal": true}, {"id": "gran_rancagua", "slug": "gran_rancagua", "nombre": "Gran Rancagua (Rancagua-Machalí)", "es_area": true, "peak_anio": 2035, "aun_creciente": true, "idx65_2024": 71.3, "idx65_2035": 118.2, "mapa_zonal": true}, {"id": "gran_santiago", "slug": "gran_santiago", "nombre": "Gran Santiago", "es_area": true, "peak_anio": 2035, "aun_creciente": true, "idx65_2024": 73.2, "idx65_2035": 109.9, "mapa_zonal": true}, {"id": "gran_valparaiso", "slug": "gran_valparaiso", "nombre": "Gran Valparaíso", "es_area": true, "peak_anio": 2035, "aun_creciente": true, "idx65_2024": 104.1, "idx65_2035": 162.3, "mapa_zonal": true}, {"id": "iquique_alto_hospicio", "slug": "iquique_alto_hospicio", "nombre": "Iquique-Alto Hospicio", "es_area": true, "peak_anio": 2035, "aun_creciente": true, "idx65_2024": 41.3, "idx65_2035": 62.1, "mapa_zonal": true}, {"id": "la_serena_coquimbo", "slug": "la_serena_coquimbo", "nombre": "La Serena-Coquimbo", "es_area": true, "peak_anio": 2035, "aun_creciente": true, "idx65_2024": 68.5, "idx65_2035": 112.4, "mapa_zonal": true}, {"id": "puerto_montt_puerto_varas", "slug": "puerto_montt_puerto_varas", "nombre": "Puerto Montt-Puerto Varas", "es_area": true, "peak_anio": 2035, "aun_creciente": true, "idx65_2024": 57.3, "idx65_2035": 99.1, "mapa_zonal": true}, {"id": "temuco_padre_las_casas", "slug": "temuco_padre_las_casas", "nombre": "Temuco-Padre Las Casas", "es_area": true, "peak_anio": 2035, "aun_creciente": true, "idx65_2024": 70.4, "idx65_2035": 113.3, "mapa_zonal": true}, {"id": "5602", "slug": "algarrobo", "nombre": "Algarrobo", "es_area": false, "peak_anio": 2035, "aun_creciente": true, "idx65_2024": 143.5, "idx65_2035": 221.7, "mapa_zonal": false}, {"id": "13502", "slug": "alhue", "nombre": "Alhué", "es_area": false, "peak_anio": 2035, "aun_creciente": true, "idx65_2024": 73.1, "idx65_2035": 111.3, "mapa_zonal": false}, {"id": "8314", "slug": "alto_biobio", "nombre": "Alto Biobío", "es_area": false, "peak_anio": 2030, "aun_creciente": false, "idx65_2024": 36.9, "idx65_2035": 61.4, "mapa_zonal": false}, {"id": "3302", "slug": "alto_del_carmen", "nombre": "Alto Del Carmen", "es_area": false, "peak_anio": 2027, "aun_creciente": false, "idx65_2024": 111.7, "idx65_2035": 191.8, "mapa_zonal": false}, {"id": "1107", "slug": "alto_hospicio", "nombre": "Alto Hospicio", "es_area": false, "peak_anio": 2035, "aun_creciente": true, "idx65_2024": 20.2, "idx65_2035": 31.2, "mapa_zonal": false}, {"id": "10202", "slug": "ancud", "nombre": "Ancud", "es_area": false, "peak_anio": 2031, "aun_creciente": false, "idx65_2024": 95.8, "idx65_2035": 167.7, "mapa_zonal": false}, {"id": "4103", "slug": "andacollo", "nombre": "Andacollo", "es_area": false, "peak_anio": 2025, "aun_creciente": false, "idx65_2024": 86.0, "idx65_2035": 142.6, "mapa_zonal": false}, {"id": "9201", "slug": "angol", "nombre": "Angol", "es_area": false, "peak_anio": 2033, "aun_creciente": false, "idx65_2024": 81.7, "idx65_2035": 132.8, "mapa_zonal": true}, {"id": "2101", "slug": "antofagasta", "nombre": "Antofagasta", "es_area": false, "peak_anio": 2035, "aun_creciente": true, "idx65_2024": 47.0, "idx65_2035": 73.2, "mapa_zonal": true}, {"id": "8302", "slug": "antuco", "nombre": "Antuco", "es_area": false, "peak_anio": 2027, "aun_creciente": false, "idx65_2024": 121.3, "idx65_2035": 207.1, "mapa_zonal": false}, {"id": "8202", "slug": "arauco", "nombre": "Arauco", "es_area": false, "peak_anio": 2031, "aun_creciente": false, "idx65_2024": 73.3, "idx65_2035": 123.1, "mapa_zonal": false}, {"id": "15101", "slug": "arica", "nombre": "Arica", "es_area": false, "peak_anio": 2035, "aun_creciente": true, "idx65_2024": 64.4, "idx65_2035": 99.9, "mapa_zonal": true}, {"id": "11201", "slug": "aysen", "nombre": "Aysén", "es_area": false, "peak_anio": 2029, "aun_creciente": false, "idx65_2024": 57.7, "idx65_2035": 96.8, "mapa_zonal": false}, {"id": "13402", "slug": "buin", "nombre": "Buin", "es_area": false, "peak_anio": 2035, "aun_creciente": true, "idx65_2024": 49.1, "idx65_2035": 73.8, "mapa_zonal": true}, {"id": "16102", "slug": "bulnes", "nombre": "Bulnes", "es_area": false, "peak_anio": 2027, "aun_creciente": false, "idx65_2024": 102.0, "idx65_2035": 168.1, "mapa_zonal": false}, {"id": "5402", "slug": "cabildo", "nombre": "Cabildo", "es_area": false, "peak_anio": 2027, "aun_creciente": false, "idx65_2024": 75.7, "idx65_2035": 118.0, "mapa_zonal": false}, {"id": "12201", "slug": "cabo_de_hornos", "nombre": "Cabo De Hornos", "es_area": false, "peak_anio": 2002, "aun_creciente": false, "idx65_2024": 16.9, "idx65_2035": 22.9, "mapa_zonal": false}, {"id": "8303", "slug": "cabrero", "nombre": "Cabrero", "es_area": false, "peak_anio": 2033, "aun_creciente": false, "idx65_2024": 84.1, "idx65_2035": 141.6, "mapa_zonal": false}, {"id": "2201", "slug": "calama", "nombre": "Calama", "es_area": false, "peak_anio": 2035, "aun_creciente": true, "idx65_2024": 38.1, "idx65_2035": 58.8, "mapa_zonal": true}, {"id": "10102", "slug": "calbuco", "nombre": "Calbuco", "es_area": false, "peak_anio": 2035, "aun_creciente": true, "idx65_2024": 88.3, "idx65_2035": 155.1, "mapa_zonal": false}, {"id": "3102", "slug": "caldera", "nombre": "Caldera", "es_area": false, "peak_anio": 2035, "aun_creciente": true, "idx65_2024": 61.5, "idx65_2035": 101.9, "mapa_zonal": false}, {"id": "5502", "slug": "calera", "nombre": "Calera", "es_area": false, "peak_anio": 2035, "aun_creciente": true, "idx65_2024": 85.2, "idx65_2035": 132.6, "mapa_zonal": true}, {"id": "13403", "slug": "calera_de_tango", "nombre": "Calera De Tango", "es_area": false, "peak_anio": 2035, "aun_creciente": true, "idx65_2024": 56.8, "idx65_2035": 85.1, "mapa_zonal": false}, {"id": "5302", "slug": "calle_larga", "nombre": "Calle Larga", "es_area": false, "peak_anio": 2035, "aun_creciente": true, "idx65_2024": 66.5, "idx65_2035": 103.1, "mapa_zonal": false}, {"id": "15102", "slug": "camarones", "nombre": "Camarones", "es_area": false, "peak_anio": 2031, "aun_creciente": false, "idx65_2024": 150.6, "idx65_2035": 232.2, "mapa_zonal": false}, {"id": "1402", "slug": "camina", "nombre": "Camiña", "es_area": false, "peak_anio": 2021, "aun_creciente": false, "idx65_2024": 99.6, "idx65_2035": 170.7, "mapa_zonal": false}, {"id": "4202", "slug": "canela", "nombre": "Canela", "es_area": false, "peak_anio": 2002, "aun_creciente": false, "idx65_2024": 152.4, "idx65_2035": 258.0, "mapa_zonal": false}, {"id": "9102", "slug": "carahue", "nombre": "Carahue", "es_area": false, "peak_anio": 2002, "aun_creciente": false, "idx65_2024": 95.6, "idx65_2035": 156.0, "mapa_zonal": false}, {"id": "5603", "slug": "cartagena", "nombre": "Cartagena", "es_area": false, "peak_anio": 2035, "aun_creciente": true, "idx65_2024": 110.0, "idx65_2035": 170.4, "mapa_zonal": false}, {"id": "5102", "slug": "casablanca", "nombre": "Casablanca", "es_area": false, "peak_anio": 2035, "aun_creciente": true, "idx65_2024": 79.8, "idx65_2035": 125.1, "mapa_zonal": false}, {"id": "10201", "slug": "castro", "nombre": "Castro", "es_area": false, "peak_anio": 2035, "aun_creciente": true, "idx65_2024": 74.6, "idx65_2035": 130.2, "mapa_zonal": false}, {"id": "5702", "slug": "catemu", "nombre": "Catemu", "es_area": false, "peak_anio": 2035, "aun_creciente": true, "idx65_2024": 83.5, "idx65_2035": 130.0, "mapa_zonal": false}, {"id": "7201", "slug": "cauquenes", "nombre": "Cauquenes", "es_area": false, "peak_anio": 2034, "aun_creciente": false, "idx65_2024": 118.6, "idx65_2035": 200.2, "mapa_zonal": true}, {"id": "8203", "slug": "canete", "nombre": "Cañete", "es_area": false, "peak_anio": 2034, "aun_creciente": false, "idx65_2024": 72.8, "idx65_2035": 122.6, "mapa_zonal": false}, {"id": "13102", "slug": "cerrillos", "nombre": "Cerrillos", "es_area": false, "peak_anio": 2035, "aun_creciente": true, "idx65_2024": 69.8, "idx65_2035": 106.2, "mapa_zonal": false}, {"id": "13103", "slug": "cerro_navia", "nombre": "Cerro Navia", "es_area": false, "peak_anio": 2002, "aun_creciente": false, "idx65_2024": 79.3, "idx65_2035": 119.4, "mapa_zonal": false}, {"id": "10401", "slug": "chaiten", "nombre": "Chaitén", "es_area": false, "peak_anio": 2002, "aun_creciente": false, "idx65_2024": 86.8, "idx65_2035": 152.8, "mapa_zonal": false}, {"id": "7202", "slug": "chanco", "nombre": "Chanco", "es_area": false, "peak_anio": 2002, "aun_creciente": false, "idx65_2024": 115.9, "idx65_2035": 194.7, "mapa_zonal": false}, {"id": "3201", "slug": "chanaral", "nombre": "Chañaral", "es_area": false, "peak_anio": 2002, "aun_creciente": false, "idx65_2024": 64.1, "idx65_2035": 108.0, "mapa_zonal": false}, {"id": "8103", "slug": "chiguayante", "nombre": "Chiguayante", "es_area": false, "peak_anio": 2032, "aun_creciente": false, "idx65_2024": 82.3, "idx65_2035": 136.7, "mapa_zonal": true}, {"id": "11401", "slug": "chile_chico", "nombre": "Chile Chico", "es_area": false, "peak_anio": 2028, "aun_creciente": false, "idx65_2024": 90.6, "idx65_2035": 152.9, "mapa_zonal": false}, {"id": "16101", "slug": "chillan", "nombre": "Chillán", "es_area": false, "peak_anio": 2035, "aun_creciente": true, "idx65_2024": 87.8, "idx65_2035": 145.1, "mapa_zonal": false}, {"id": "16103", "slug": "chillan_viejo", "nombre": "Chillán Viejo", "es_area": false, "peak_anio": 2035, "aun_creciente": true, "idx65_2024": 59.6, "idx65_2035": 97.5, "mapa_zonal": false}, {"id": "6303", "slug": "chimbarongo", "nombre": "Chimbarongo", "es_area": false, "peak_anio": 2035, "aun_creciente": true, "idx65_2024": 85.3, "idx65_2035": 144.2, "mapa_zonal": true}, {"id": "9121", "slug": "cholchol", "nombre": "Cholchol", "es_area": false, "peak_anio": 2035, "aun_creciente": true, "idx65_2024": 85.3, "idx65_2035": 140.2, "mapa_zonal": false}, {"id": "10203", "slug": "chonchi", "nombre": "Chonchi", "es_area": false, "peak_anio": 2035, "aun_creciente": true, "idx65_2024": 85.3, "idx65_2035": 149.0, "mapa_zonal": false}, {"id": "6302", "slug": "chepica", "nombre": "Chépica", "es_area": false, "peak_anio": 2035, "aun_creciente": true, "idx65_2024": 112.9, "idx65_2035": 192.8, "mapa_zonal": false}, {"id": "11202", "slug": "cisnes", "nombre": "Cisnes", "es_area": false, "peak_anio": 2029, "aun_creciente": false, "idx65_2024": 57.6, "idx65_2035": 95.5, "mapa_zonal": false}, {"id": "16202", "slug": "cobquecura", "nombre": "Cobquecura", "es_area": false, "peak_anio": 2002, "aun_creciente": false, "idx65_2024": 193.7, "idx65_2035": 320.9, "mapa_zonal": false}, {"id": "10103", "slug": "cochamo", "nombre": "Cochamó", "es_area": false, "peak_anio": 2002, "aun_creciente": false, "idx65_2024": 143.2, "idx65_2035": 251.0, "mapa_zonal": false}, {"id": "11301", "slug": "cochrane", "nombre": "Cochrane", "es_area": false, "peak_anio": 2032, "aun_creciente": false, "idx65_2024": 69.9, "idx65_2035": 117.6, "mapa_zonal": false}, {"id": "6102", "slug": "codegua", "nombre": "Codegua", "es_area": false, "peak_anio": 2035, "aun_creciente": true, "idx65_2024": 71.8, "idx65_2035": 120.6, "mapa_zonal": false}, {"id": "16203", "slug": "coelemu", "nombre": "Coelemu", "es_area": false, "peak_anio": 2026, "aun_creciente": false, "idx65_2024": 105.8, "idx65_2035": 175.9, "mapa_zonal": false}, {"id": "16302", "slug": "coihueco", "nombre": "Coihueco", "es_area": false, "peak_anio": 2035, "aun_creciente": true, "idx65_2024": 78.0, "idx65_2035": 129.2, "mapa_zonal": false}, {"id": "6103", "slug": "coinco", "nombre": "Coinco", "es_area": false, "peak_anio": 2035, "aun_creciente": true, "idx65_2024": 112.1, "idx65_2035": 191.2, "mapa_zonal": false}, {"id": "7402", "slug": "colbun", "nombre": "Colbún", "es_area": false, "peak_anio": 2035, "aun_creciente": true, "idx65_2024": 90.9, "idx65_2035": 148.3, "mapa_zonal": false}, {"id": "1403", "slug": "colchane", "nombre": "Colchane", "es_area": false, "peak_anio": 2002, "aun_creciente": false, "idx65_2024": 124.3, "idx65_2035": 202.2, "mapa_zonal": false}, {"id": "13301", "slug": "colina", "nombre": "Colina", "es_area": false, "peak_anio": 2035, "aun_creciente": true, "idx65_2024": 28.1, "idx65_2035": 41.6, "mapa_zonal": true}, {"id": "9202", "slug": "collipulli", "nombre": "Collipulli", "es_area": false, "peak_anio": 2035, "aun_creciente": true, "idx65_2024": 73.3, "idx65_2035": 118.7, "mapa_zonal": false}, {"id": "6104", "slug": "coltauco", "nombre": "Coltauco", "es_area": false, "peak_anio": 2035, "aun_creciente": true, "idx65_2024": 87.5, "idx65_2035": 148.2, "mapa_zonal": false}, {"id": "4302", "slug": "combarbala", "nombre": "Combarbalá", "es_area": false, "peak_anio": 2002, "aun_creciente": false, "idx65_2024": 144.0, "idx65_2035": 243.0, "mapa_zonal": false}, {"id": "8101", "slug": "concepcion", "nombre": "Concepción", "es_area": false, "peak_anio": 2031, "aun_creciente": false, "idx65_2024": 113.9, "idx65_2035": 191.0, "mapa_zonal": true}, {"id": "13104", "slug": "conchali", "nombre": "Conchalí", "es_area": false, "peak_anio": 2002, "aun_creciente": false, "idx65_2024": 93.0, "idx65_2035": 143.0, "mapa_zonal": false}, {"id": "5103", "slug": "concon", "nombre": "Concón", "es_area": false, "peak_anio": 2035, "aun_creciente": true, "idx65_2024": 79.7, "idx65_2035": 123.0, "mapa_zonal": false}, {"id": "7102", "slug": "constitucion", "nombre": "Constitución", "es_area": false, "peak_anio": 2027, "aun_creciente": false, "idx65_2024": 64.5, "idx65_2035": 104.5, "mapa_zonal": true}, {"id": "8204", "slug": "contulmo", "nombre": "Contulmo", "es_area": false, "peak_anio": 2028, "aun_creciente": false, "idx65_2024": 101.0, "idx65_2035": 172.3, "mapa_zonal": false}, {"id": "3101", "slug": "copiapo", "nombre": "Copiapó", "es_area": false, "peak_anio": 2035, "aun_creciente": true, "idx65_2024": 53.1, "idx65_2035": 88.2, "mapa_zonal": true}, {"id": "4102", "slug": "coquimbo", "nombre": "Coquimbo", "es_area": false, "peak_anio": 2035, "aun_creciente": true, "idx65_2024": 65.8, "idx65_2035": 107.7, "mapa_zonal": false}, {"id": "8102", "slug": "coronel", "nombre": "Coronel", "es_area": false, "peak_anio": 2035, "aun_creciente": true, "idx65_2024": 62.7, "idx65_2035": 104.4, "mapa_zonal": true}, {"id": "14102", "slug": "corral", "nombre": "Corral", "es_area": false, "peak_anio": 2002, "aun_creciente": false, "idx65_2024": 116.5, "idx65_2035": 192.0, "mapa_zonal": false}, {"id": "11101", "slug": "coyhaique", "nombre": "Coyhaique", "es_area": false, "peak_anio": 2032, "aun_creciente": false, "idx65_2024": 59.2, "idx65_2035": 98.9, "mapa_zonal": true}, {"id": "9103", "slug": "cunco", "nombre": "Cunco", "es_area": false, "peak_anio": 2002, "aun_creciente": false, "idx65_2024": 122.9, "idx65_2035": 200.4, "mapa_zonal": false}, {"id": "9203", "slug": "curacautin", "nombre": "Curacautín", "es_area": false, "peak_anio": 2024, "aun_creciente": false, "idx65_2024": 110.2, "idx65_2035": 178.9, "mapa_zonal": false}, {"id": "13503", "slug": "curacavi", "nombre": "Curacaví", "es_area": false, "peak_anio": 2035, "aun_creciente": true, "idx65_2024": 72.6, "idx65_2035": 109.8, "mapa_zonal": false}, {"id": "10204", "slug": "curaco_de_velez", "nombre": "Curaco De Vélez", "es_area": false, "peak_anio": 2035, "aun_creciente": true, "idx65_2024": 107.5, "idx65_2035": 190.9, "mapa_zonal": false}, {"id": "8205", "slug": "curanilahue", "nombre": "Curanilahue", "es_area": false, "peak_anio": 2026, "aun_creciente": false, "idx65_2024": 75.8, "idx65_2035": 126.8, "mapa_zonal": false}, {"id": "9104", "slug": "curarrehue", "nombre": "Curarrehue", "es_area": false, "peak_anio": 2029, "aun_creciente": false, "idx65_2024": 74.0, "idx65_2035": 120.5, "mapa_zonal": false}, {"id": "7103", "slug": "curepto", "nombre": "Curepto", "es_area": false, "peak_anio": 2002, "aun_creciente": false, "idx65_2024": 187.1, "idx65_2035": 318.4, "mapa_zonal": false}, {"id": "7301", "slug": "curico", "nombre": "Curicó", "es_area": false, "peak_anio": 2035, "aun_creciente": true, "idx65_2024": 73.7, "idx65_2035": 120.5, "mapa_zonal": true}, {"id": "10205", "slug": "dalcahue", "nombre": "Dalcahue", "es_area": false, "peak_anio": 2035, "aun_creciente": true, "idx65_2024": 77.4, "idx65_2035": 136.1, "mapa_zonal": false}, {"id": "3202", "slug": "diego_de_almagro", "nombre": "Diego De Almagro", "es_area": false, "peak_anio": 2002, "aun_creciente": false, "idx65_2024": 41.0, "idx65_2035": 67.1, "mapa_zonal": false}, {"id": "6105", "slug": "donihue", "nombre": "Doñihue", "es_area": false, "peak_anio": 2035, "aun_creciente": true, "idx65_2024": 77.6, "idx65_2035": 130.6, "mapa_zonal": false}, {"id": "13105", "slug": "el_bosque", "nombre": "El Bosque", "es_area": false, "peak_anio": 2002, "aun_creciente": false, "idx65_2024": 76.2, "idx65_2035": 115.0, "mapa_zonal": false}, {"id": "16104", "slug": "el_carmen", "nombre": "El Carmen", "es_area": false, "peak_anio": 2002, "aun_creciente": false, "idx65_2024": 120.2, "idx65_2035": 201.8, "mapa_zonal": false}, {"id": "13602", "slug": "el_monte", "nombre": "El Monte", "es_area": false, "peak_anio": 2035, "aun_creciente": true, "idx65_2024": 57.0, "idx65_2035": 86.2, "mapa_zonal": false}, {"id": "5604", "slug": "el_quisco", "nombre": "El Quisco", "es_area": false, "peak_anio": 2035, "aun_creciente": true, "idx65_2024": 156.1, "idx65_2035": 244.5, "mapa_zonal": false}, {"id": "5605", "slug": "el_tabo", "nombre": "El Tabo", "es_area": false, "peak_anio": 2035, "aun_creciente": true, "idx65_2024": 170.2, "idx65_2035": 261.7, "mapa_zonal": true}, {"id": "7104", "slug": "empedrado", "nombre": "Empedrado", "es_area": false, "peak_anio": 2002, "aun_creciente": false, "idx65_2024": 89.3, "idx65_2035": 147.5, "mapa_zonal": false}, {"id": "9204", "slug": "ercilla", "nombre": "Ercilla", "es_area": false, "peak_anio": 2002, "aun_creciente": false, "idx65_2024": 82.6, "idx65_2035": 134.5, "mapa_zonal": false}, {"id": "13106", "slug": "estacion_central", "nombre": "Estación Central", "es_area": false, "peak_anio": 2035, "aun_creciente": true, "idx65_2024": 85.8, "idx65_2035": 131.5, "mapa_zonal": false}, {"id": "8104", "slug": "florida", "nombre": "Florida", "es_area": false, "peak_anio": 2026, "aun_creciente": false, "idx65_2024": 140.8, "idx65_2035": 236.6, "mapa_zonal": false}, {"id": "9105", "slug": "freire", "nombre": "Freire", "es_area": false, "peak_anio": 2024, "aun_creciente": false, "idx65_2024": 98.7, "idx65_2035": 160.5, "mapa_zonal": false}, {"id": "3303", "slug": "freirina", "nombre": "Freirina", "es_area": false, "peak_anio": 2035, "aun_creciente": true, "idx65_2024": 74.6, "idx65_2035": 125.7, "mapa_zonal": false}, {"id": "10104", "slug": "fresia", "nombre": "Fresia", "es_area": false, "peak_anio": 2002, "aun_creciente": false, "idx65_2024": 116.6, "idx65_2035": 204.5, "mapa_zonal": false}, {"id": "10105", "slug": "frutillar", "nombre": "Frutillar", "es_area": false, "peak_anio": 2035, "aun_creciente": true, "idx65_2024": 82.0, "idx65_2035": 143.0, "mapa_zonal": false}, {"id": "10402", "slug": "futaleufu", "nombre": "Futaleufú", "es_area": false, "peak_anio": 2035, "aun_creciente": true, "idx65_2024": 94.8, "idx65_2035": 166.9, "mapa_zonal": false}, {"id": "14202", "slug": "futrono", "nombre": "Futrono", "es_area": false, "peak_anio": 2002, "aun_creciente": false, "idx65_2024": 75.5, "idx65_2035": 122.8, "mapa_zonal": false}, {"id": "9106", "slug": "galvarino", "nombre": "Galvarino", "es_area": false, "peak_anio": 2002, "aun_creciente": false, "idx65_2024": 87.0, "idx65_2035": 143.8, "mapa_zonal": false}, {"id": "15202", "slug": "general_lagos", "nombre": "General Lagos", "es_area": false, "peak_anio": 2002, "aun_creciente": false, "idx65_2024": 131.8, "idx65_2035": 202.3, "mapa_zonal": false}, {"id": "9107", "slug": "gorbea", "nombre": "Gorbea", "es_area": false, "peak_anio": 2002, "aun_creciente": false, "idx65_2024": 126.4, "idx65_2035": 207.0, "mapa_zonal": false}, {"id": "6106", "slug": "graneros", "nombre": "Graneros", "es_area": false, "peak_anio": 2035, "aun_creciente": true, "idx65_2024": 59.4, "idx65_2035": 99.5, "mapa_zonal": false}, {"id": "11203", "slug": "guaitecas", "nombre": "Guaitecas", "es_area": false, "peak_anio": 2027, "aun_creciente": false, "idx65_2024": 49.5, "idx65_2035": 83.5, "mapa_zonal": false}, {"id": "5503", "slug": "hijuelas", "nombre": "Hijuelas", "es_area": false, "peak_anio": 2035, "aun_creciente": true, "idx65_2024": 75.4, "idx65_2035": 117.0, "mapa_zonal": false}, {"id": "10403", "slug": "hualaihue", "nombre": "Hualaihué", "es_area": false, "peak_anio": 2030, "aun_creciente": false, "idx65_2024": 74.1, "idx65_2035": 129.8, "mapa_zonal": false}, {"id": "7302", "slug": "hualane", "nombre": "Hualañé", "es_area": false, "peak_anio": 2021, "aun_creciente": false, "idx65_2024": 131.2, "idx65_2035": 218.1, "mapa_zonal": false}, {"id": "8112", "slug": "hualpen", "nombre": "Hualpén", "es_area": false, "peak_anio": 2031, "aun_creciente": false, "idx65_2024": 94.0, "idx65_2035": 157.5, "mapa_zonal": true}, {"id": "8105", "slug": "hualqui", "nombre": "Hualqui", "es_area": false, "peak_anio": 2035, "aun_creciente": true, "idx65_2024": 73.8, "idx65_2035": 124.4, "mapa_zonal": false}, {"id": "1404", "slug": "huara", "nombre": "Huara", "es_area": false, "peak_anio": 2035, "aun_creciente": true, "idx65_2024": 86.9, "idx65_2035": 143.0, "mapa_zonal": false}, {"id": "3304", "slug": "huasco", "nombre": "Huasco", "es_area": false, "peak_anio": 2035, "aun_creciente": true, "idx65_2024": 74.5, "idx65_2035": 124.3, "mapa_zonal": false}, {"id": "13107", "slug": "huechuraba", "nombre": "Huechuraba", "es_area": false, "peak_anio": 2035, "aun_creciente": true, "idx65_2024": 51.0, "idx65_2035": 76.2, "mapa_zonal": false}, {"id": "4201", "slug": "illapel", "nombre": "Illapel", "es_area": false, "peak_anio": 2034, "aun_creciente": false, "idx65_2024": 89.8, "idx65_2035": 148.1, "mapa_zonal": false}, {"id": "13108", "slug": "independencia", "nombre": "Independencia", "es_area": false, "peak_anio": 2035, "aun_creciente": true, "idx65_2024": 80.4, "idx65_2035": 122.9, "mapa_zonal": false}, {"id": "1101", "slug": "iquique", "nombre": "Iquique", "es_area": false, "peak_anio": 2035, "aun_creciente": true, "idx65_2024": 59.4, "idx65_2035": 95.3, "mapa_zonal": false}, {"id": "13603", "slug": "isla_de_maipo", "nombre": "Isla De Maipo", "es_area": false, "peak_anio": 2035, "aun_creciente": true, "idx65_2024": 58.2, "idx65_2035": 87.5, "mapa_zonal": false}, {"id": "5201", "slug": "isla_de_pascua", "nombre": "Isla De Pascua", "es_area": false, "peak_anio": 2035, "aun_creciente": true, "idx65_2024": 34.7, "idx65_2035": 50.4, "mapa_zonal": false}, {"id": "5104", "slug": "juan_fernandez", "nombre": "Juan Fernández", "es_area": false, "peak_anio": 2035, "aun_creciente": true, "idx65_2024": 60.8, "idx65_2035": 93.0, "mapa_zonal": false}, {"id": "13109", "slug": "la_cisterna", "nombre": "La Cisterna", "es_area": false, "peak_anio": 2024, "aun_creciente": false, "idx65_2024": 101.2, "idx65_2035": 154.9, "mapa_zonal": false}, {"id": "5504", "slug": "la_cruz", "nombre": "La Cruz", "es_area": false, "peak_anio": 2035, "aun_creciente": true, "idx65_2024": 60.5, "idx65_2035": 93.9, "mapa_zonal": false}, {"id": "6202", "slug": "la_estrella", "nombre": "La Estrella", "es_area": false, "peak_anio": 2002, "aun_creciente": false, "idx65_2024": 158.8, "idx65_2035": 265.6, "mapa_zonal": false}, {"id": "13110", "slug": "la_florida", "nombre": "La Florida", "es_area": false, "peak_anio": 2032, "aun_creciente": false, "idx65_2024": 88.2, "idx65_2035": 131.3, "mapa_zonal": false}, {"id": "13111", "slug": "la_granja", "nombre": "La Granja", "es_area": false, "peak_anio": 2002, "aun_creciente": false, "idx65_2024": 78.2, "idx65_2035": 117.5, "mapa_zonal": false}, {"id": "4104", "slug": "la_higuera", "nombre": "La Higuera", "es_area": false, "peak_anio": 2035, "aun_creciente": true, "idx65_2024": 83.7, "idx65_2035": 135.5, "mapa_zonal": false}, {"id": "5401", "slug": "la_ligua", "nombre": "La Ligua", "es_area": false, "peak_anio": 2035, "aun_creciente": true, "idx65_2024": 89.8, "idx65_2035": 140.1, "mapa_zonal": false}, {"id": "13112", "slug": "la_pintana", "nombre": "La Pintana", "es_area": false, "peak_anio": 2002, "aun_creciente": false, "idx65_2024": 49.8, "idx65_2035": 73.2, "mapa_zonal": false}, {"id": "13113", "slug": "la_reina", "nombre": "La Reina", "es_area": false, "peak_anio": 2021, "aun_creciente": false, "idx65_2024": 101.6, "idx65_2035": 154.6, "mapa_zonal": false}, {"id": "4101", "slug": "la_serena", "nombre": "La Serena", "es_area": false, "peak_anio": 2035, "aun_creciente": true, "idx65_2024": 71.4, "idx65_2035": 117.6, "mapa_zonal": false}, {"id": "14201", "slug": "la_union", "nombre": "La Unión", "es_area": false, "peak_anio": 2002, "aun_creciente": false, "idx65_2024": 97.0, "idx65_2035": 157.9, "mapa_zonal": false}, {"id": "14203", "slug": "lago_ranco", "nombre": "Lago Ranco", "es_area": false, "peak_anio": 2002, "aun_creciente": false, "idx65_2024": 100.4, "idx65_2035": 164.6, "mapa_zonal": false}, {"id": "11102", "slug": "lago_verde", "nombre": "Lago Verde", "es_area": false, "peak_anio": 2002, "aun_creciente": false, "idx65_2024": 125.7, "idx65_2035": 205.6, "mapa_zonal": false}, {"id": "12102", "slug": "laguna_blanca", "nombre": "Laguna Blanca", "es_area": false, "peak_anio": 2002, "aun_creciente": false, "idx65_2024": 90.0, "idx65_2035": 123.3, "mapa_zonal": false}, {"id": "8304", "slug": "laja", "nombre": "Laja", "es_area": false, "peak_anio": 2026, "aun_creciente": false, "idx65_2024": 90.7, "idx65_2035": 151.7, "mapa_zonal": false}, {"id": "13302", "slug": "lampa", "nombre": "Lampa", "es_area": false, "peak_anio": 2035, "aun_creciente": true, "idx65_2024": 27.8, "idx65_2035": 41.5, "mapa_zonal": true}, {"id": "14103", "slug": "lanco", "nombre": "Lanco", "es_area": false, "peak_anio": 2035, "aun_creciente": true, "idx65_2024": 84.4, "idx65_2035": 138.5, "mapa_zonal": false}, {"id": "6107", "slug": "las_cabras", "nombre": "Las Cabras", "es_area": false, "peak_anio": 2035, "aun_creciente": true, "idx65_2024": 94.3, "idx65_2035": 160.6, "mapa_zonal": false}, {"id": "13114", "slug": "las_condes", "nombre": "Las Condes", "es_area": false, "peak_anio": 2035, "aun_creciente": true, "idx65_2024": 125.3, "idx65_2035": 193.3, "mapa_zonal": false}, {"id": "9108", "slug": "lautaro", "nombre": "Lautaro", "es_area": false, "peak_anio": 2035, "aun_creciente": true, "idx65_2024": 72.3, "idx65_2035": 117.3, "mapa_zonal": false}, {"id": "8201", "slug": "lebu", "nombre": "Lebu", "es_area": false, "peak_anio": 2025, "aun_creciente": false, "idx65_2024": 70.5, "idx65_2035": 118.3, "mapa_zonal": false}, {"id": "7303", "slug": "licanten", "nombre": "Licantén", "es_area": false, "peak_anio": 2002, "aun_creciente": false, "idx65_2024": 111.1, "idx65_2035": 184.5, "mapa_zonal": false}, {"id": "5802", "slug": "limache", "nombre": "Limache", "es_area": false, "peak_anio": 2035, "aun_creciente": true, "idx65_2024": 91.3, "idx65_2035": 143.1, "mapa_zonal": true}, {"id": "7401", "slug": "linares", "nombre": "Linares", "es_area": false, "peak_anio": 2035, "aun_creciente": true, "idx65_2024": 84.4, "idx65_2035": 138.9, "mapa_zonal": true}, {"id": "6203", "slug": "litueche", "nombre": "Litueche", "es_area": false, "peak_anio": 2035, "aun_creciente": true, "idx65_2024": 127.2, "idx65_2035": 213.6, "mapa_zonal": false}, {"id": "5703", "slug": "llaillay", "nombre": "Llaillay", "es_area": false, "peak_anio": 2035, "aun_creciente": true, "idx65_2024": 77.5, "idx65_2035": 120.5, "mapa_zonal": false}, {"id": "10107", "slug": "llanquihue", "nombre": "Llanquihue", "es_area": false, "peak_anio": 2035, "aun_creciente": true, "idx65_2024": 84.9, "idx65_2035": 147.3, "mapa_zonal": false}, {"id": "13115", "slug": "lo_barnechea", "nombre": "Lo Barnechea", "es_area": false, "peak_anio": 2035, "aun_creciente": true, "idx65_2024": 40.3, "idx65_2035": 59.8, "mapa_zonal": false}, {"id": "13116", "slug": "lo_espejo", "nombre": "Lo Espejo", "es_area": false, "peak_anio": 2002, "aun_creciente": false, "idx65_2024": 75.4, "idx65_2035": 115.2, "mapa_zonal": false}, {"id": "13117", "slug": "lo_prado", "nombre": "Lo Prado", "es_area": false, "peak_anio": 2002, "aun_creciente": false, "idx65_2024": 101.6, "idx65_2035": 154.0, "mapa_zonal": false}, {"id": "6304", "slug": "lolol", "nombre": "Lolol", "es_area": false, "peak_anio": 2035, "aun_creciente": true, "idx65_2024": 144.4, "idx65_2035": 248.7, "mapa_zonal": false}, {"id": "9109", "slug": "loncoche", "nombre": "Loncoche", "es_area": false, "peak_anio": 2024, "aun_creciente": false, "idx65_2024": 95.0, "idx65_2035": 154.7, "mapa_zonal": false}, {"id": "7403", "slug": "longavi", "nombre": "Longaví", "es_area": false, "peak_anio": 2035, "aun_creciente": true, "idx65_2024": 93.5, "idx65_2035": 152.3, "mapa_zonal": false}, {"id": "9205", "slug": "lonquimay", "nombre": "Lonquimay", "es_area": false, "peak_anio": 2029, "aun_creciente": false, "idx65_2024": 78.9, "idx65_2035": 128.4, "mapa_zonal": false}, {"id": "5301", "slug": "los_andes", "nombre": "Los Andes", "es_area": false, "peak_anio": 2035, "aun_creciente": true, "idx65_2024": 80.2, "idx65_2035": 123.5, "mapa_zonal": true}, {"id": "14104", "slug": "los_lagos", "nombre": "Los Lagos", "es_area": false, "peak_anio": 2002, "aun_creciente": false, "idx65_2024": 85.6, "idx65_2035": 138.9, "mapa_zonal": false}, {"id": "10106", "slug": "los_muermos", "nombre": "Los Muermos", "es_area": false, "peak_anio": 2024, "aun_creciente": false, "idx65_2024": 109.3, "idx65_2035": 191.9, "mapa_zonal": false}, {"id": "9206", "slug": "los_sauces", "nombre": "Los Sauces", "es_area": false, "peak_anio": 2002, "aun_creciente": false, "idx65_2024": 109.3, "idx65_2035": 179.7, "mapa_zonal": false}, {"id": "4203", "slug": "los_vilos", "nombre": "Los Vilos", "es_area": false, "peak_anio": 2035, "aun_creciente": true, "idx65_2024": 85.3, "idx65_2035": 141.5, "mapa_zonal": false}, {"id": "8206", "slug": "los_alamos", "nombre": "Los Álamos", "es_area": false, "peak_anio": 2035, "aun_creciente": true, "idx65_2024": 62.0, "idx65_2035": 104.0, "mapa_zonal": false}, {"id": "8301", "slug": "los_angeles", "nombre": "Los Ángeles", "es_area": false, "peak_anio": 2035, "aun_creciente": true, "idx65_2024": 70.4, "idx65_2035": 118.1, "mapa_zonal": true}, {"id": "8106", "slug": "lota", "nombre": "Lota", "es_area": false, "peak_anio": 2002, "aun_creciente": false, "idx65_2024": 91.3, "idx65_2035": 151.9, "mapa_zonal": true}, {"id": "9207", "slug": "lumaco", "nombre": "Lumaco", "es_area": false, "peak_anio": 2002, "aun_creciente": false, "idx65_2024": 92.4, "idx65_2035": 151.1, "mapa_zonal": false}, {"id": "6108", "slug": "machali", "nombre": "Machalí", "es_area": false, "peak_anio": 2035, "aun_creciente": true, "idx65_2024": 47.4, "idx65_2035": 78.4, "mapa_zonal": false}, {"id": "13118", "slug": "macul", "nombre": "Macul", "es_area": false, "peak_anio": 2035, "aun_creciente": true, "idx65_2024": 109.1, "idx65_2035": 166.5, "mapa_zonal": false}, {"id": "13119", "slug": "maipu", "nombre": "Maipú", "es_area": false, "peak_anio": 2035, "aun_creciente": true, "idx65_2024": 61.1, "idx65_2035": 90.6, "mapa_zonal": false}, {"id": "6109", "slug": "malloa", "nombre": "Malloa", "es_area": false, "peak_anio": 2035, "aun_creciente": true, "idx65_2024": 104.2, "idx65_2035": 175.9, "mapa_zonal": false}, {"id": "6204", "slug": "marchihue", "nombre": "Marchihue", "es_area": false, "peak_anio": 2035, "aun_creciente": true, "idx65_2024": 138.2, "idx65_2035": 235.9, "mapa_zonal": false}, {"id": "14106", "slug": "mariquina", "nombre": "Mariquina", "es_area": false, "peak_anio": 2035, "aun_creciente": true, "idx65_2024": 71.3, "idx65_2035": 116.4, "mapa_zonal": false}, {"id": "2302", "slug": "maria_elena", "nombre": "María Elena", "es_area": false, "peak_anio": 2002, "aun_creciente": false, "idx65_2024": 36.0, "idx65_2035": 54.2, "mapa_zonal": false}, {"id": "13504", "slug": "maria_pinto", "nombre": "María Pinto", "es_area": false, "peak_anio": 2035, "aun_creciente": true, "idx65_2024": 70.3, "idx65_2035": 106.8, "mapa_zonal": false}, {"id": "7105", "slug": "maule", "nombre": "Maule", "es_area": false, "peak_anio": 2035, "aun_creciente": true, "idx65_2024": 36.5, "idx65_2035": 59.1, "mapa_zonal": true}, {"id": "10108", "slug": "maullin", "nombre": "Maullín", "es_area": false, "peak_anio": 2002, "aun_creciente": false, "idx65_2024": 133.5, "idx65_2035": 234.4, "mapa_zonal": false}, {"id": "2102", "slug": "mejillones", "nombre": "Mejillones", "es_area": false, "peak_anio": 2035, "aun_creciente": true, "idx65_2024": 36.7, "idx65_2035": 56.3, "mapa_zonal": false}, {"id": "9110", "slug": "melipeuco", "nombre": "Melipeuco", "es_area": false, "peak_anio": 2030, "aun_creciente": false, "idx65_2024": 119.9, "idx65_2035": 195.3, "mapa_zonal": false}, {"id": "13501", "slug": "melipilla", "nombre": "Melipilla", "es_area": false, "peak_anio": 2035, "aun_creciente": true, "idx65_2024": 68.8, "idx65_2035": 104.3, "mapa_zonal": true}, {"id": "7304", "slug": "molina", "nombre": "Molina", "es_area": false, "peak_anio": 2035, "aun_creciente": true, "idx65_2024": 83.3, "idx65_2035": 136.5, "mapa_zonal": false}, {"id": "4303", "slug": "monte_patria", "nombre": "Monte Patria", "es_area": false, "peak_anio": 2028, "aun_creciente": false, "idx65_2024": 83.1, "idx65_2035": 138.6, "mapa_zonal": false}, {"id": "6110", "slug": "mostazal", "nombre": "Mostazal", "es_area": false, "peak_anio": 2035, "aun_creciente": true, "idx65_2024": 75.3, "idx65_2035": 126.3, "mapa_zonal": false}, {"id": "8305", "slug": "mulchen", "nombre": "Mulchén", "es_area": false, "peak_anio": 2026, "aun_creciente": false, "idx65_2024": 86.6, "idx65_2035": 146.7, "mapa_zonal": false}, {"id": "14105", "slug": "mafil", "nombre": "Máfil", "es_area": false, "peak_anio": 2002, "aun_creciente": false, "idx65_2024": 91.4, "idx65_2035": 149.2, "mapa_zonal": false}, {"id": "8306", "slug": "nacimiento", "nombre": "Nacimiento", "es_area": false, "peak_anio": 2028, "aun_creciente": false, "idx65_2024": 78.1, "idx65_2035": 131.9, "mapa_zonal": false}, {"id": "6305", "slug": "nancagua", "nombre": "Nancagua", "es_area": false, "peak_anio": 2035, "aun_creciente": true, "idx65_2024": 90.4, "idx65_2035": 153.7, "mapa_zonal": false}, {"id": "12401", "slug": "natales", "nombre": "Natales", "es_area": false, "peak_anio": 2035, "aun_creciente": true, "idx65_2024": 94.2, "idx65_2035": 141.3, "mapa_zonal": false}, {"id": "6205", "slug": "navidad", "nombre": "Navidad", "es_area": false, "peak_anio": 2035, "aun_creciente": true, "idx65_2024": 191.2, "idx65_2035": 329.1, "mapa_zonal": false}, {"id": "8307", "slug": "negrete", "nombre": "Negrete", "es_area": false, "peak_anio": 2034, "aun_creciente": false, "idx65_2024": 82.4, "idx65_2035": 138.6, "mapa_zonal": false}, {"id": "16204", "slug": "ninhue", "nombre": "Ninhue", "es_area": false, "peak_anio": 2002, "aun_creciente": false, "idx65_2024": 162.5, "idx65_2035": 271.6, "mapa_zonal": false}, {"id": "5506", "slug": "nogales", "nombre": "Nogales", "es_area": false, "peak_anio": 2032, "aun_creciente": false, "idx65_2024": 84.5, "idx65_2035": 131.3, "mapa_zonal": false}, {"id": "9111", "slug": "nueva_imperial", "nombre": "Nueva Imperial", "es_area": false, "peak_anio": 2032, "aun_creciente": false, "idx65_2024": 89.2, "idx65_2035": 145.9, "mapa_zonal": false}, {"id": "11302", "slug": "o_higgins", "nombre": "O'higgins", "es_area": false, "peak_anio": 2035, "aun_creciente": true, "idx65_2024": 46.2, "idx65_2035": 72.7, "mapa_zonal": false}, {"id": "6111", "slug": "olivar", "nombre": "Olivar", "es_area": false, "peak_anio": 2035, "aun_creciente": true, "idx65_2024": 73.4, "idx65_2035": 122.3, "mapa_zonal": false}, {"id": "2202", "slug": "ollague", "nombre": "Ollagüe", "es_area": false, "peak_anio": 2002, "aun_creciente": false, "idx65_2024": 62.7, "idx65_2035": 127.3, "mapa_zonal": false}, {"id": "5803", "slug": "olmue", "nombre": "Olmué", "es_area": false, "peak_anio": 2035, "aun_creciente": true, "idx65_2024": 112.2, "idx65_2035": 174.4, "mapa_zonal": false}, {"id": "10301", "slug": "osorno", "nombre": "Osorno", "es_area": false, "peak_anio": 2035, "aun_creciente": true, "idx65_2024": 83.5, "idx65_2035": 145.4, "mapa_zonal": true}, {"id": "4301", "slug": "ovalle", "nombre": "Ovalle", "es_area": false, "peak_anio": 2035, "aun_creciente": true, "idx65_2024": 75.4, "idx65_2035": 125.5, "mapa_zonal": true}, {"id": "13604", "slug": "padre_hurtado", "nombre": "Padre Hurtado", "es_area": false, "peak_anio": 2035, "aun_creciente": true, "idx65_2024": 49.8, "idx65_2035": 74.7, "mapa_zonal": true}, {"id": "9112", "slug": "padre_las_casas", "nombre": "Padre Las Casas", "es_area": false, "peak_anio": 2035, "aun_creciente": true, "idx65_2024": 57.9, "idx65_2035": 93.3, "mapa_zonal": false}, {"id": "4105", "slug": "paihuano", "nombre": "Paihuano", "es_area": false, "peak_anio": 2029, "aun_creciente": false, "idx65_2024": 108.5, "idx65_2035": 183.1, "mapa_zonal": false}, {"id": "14107", "slug": "paillaco", "nombre": "Paillaco", "es_area": false, "peak_anio": 2029, "aun_creciente": false, "idx65_2024": 92.6, "idx65_2035": 151.5, "mapa_zonal": false}, {"id": "13404", "slug": "paine", "nombre": "Paine", "es_area": false, "peak_anio": 2035, "aun_creciente": true, "idx65_2024": 55.5, "idx65_2035": 83.0, "mapa_zonal": true}, {"id": "10404", "slug": "palena", "nombre": "Palena", "es_area": false, "peak_anio": 2020, "aun_creciente": false, "idx65_2024": 126.1, "idx65_2035": 223.2, "mapa_zonal": false}, {"id": "6306", "slug": "palmilla", "nombre": "Palmilla", "es_area": false, "peak_anio": 2035, "aun_creciente": true, "idx65_2024": 99.9, "idx65_2035": 169.5, "mapa_zonal": false}, {"id": "14108", "slug": "panguipulli", "nombre": "Panguipulli", "es_area": false, "peak_anio": 2028, "aun_creciente": false, "idx65_2024": 83.6, "idx65_2035": 136.2, "mapa_zonal": false}, {"id": "5704", "slug": "panquehue", "nombre": "Panquehue", "es_area": false, "peak_anio": 2035, "aun_creciente": true, "idx65_2024": 75.3, "idx65_2035": 115.0, "mapa_zonal": false}, {"id": "5403", "slug": "papudo", "nombre": "Papudo", "es_area": false, "peak_anio": 2035, "aun_creciente": true, "idx65_2024": 91.7, "idx65_2035": 143.5, "mapa_zonal": false}, {"id": "6206", "slug": "paredones", "nombre": "Paredones", "es_area": false, "peak_anio": 2002, "aun_creciente": false, "idx65_2024": 177.1, "idx65_2035": 309.7, "mapa_zonal": false}, {"id": "7404", "slug": "parral", "nombre": "Parral", "es_area": false, "peak_anio": 2035, "aun_creciente": true, "idx65_2024": 93.9, "idx65_2035": 155.7, "mapa_zonal": false}, {"id": "13121", "slug": "pedro_aguirre_cerda", "nombre": "Pedro Aguirre Cerda", "es_area": false, "peak_anio": 2002, "aun_creciente": false, "idx65_2024": 99.9, "idx65_2035": 152.8, "mapa_zonal": false}, {"id": "7106", "slug": "pelarco", "nombre": "Pelarco", "es_area": false, "peak_anio": 2035, "aun_creciente": true, "idx65_2024": 106.3, "idx65_2035": 176.6, "mapa_zonal": false}, {"id": "7203", "slug": "pelluhue", "nombre": "Pelluhue", "es_area": false, "peak_anio": 2035, "aun_creciente": true, "idx65_2024": 117.3, "idx65_2035": 193.7, "mapa_zonal": false}, {"id": "16105", "slug": "pemuco", "nombre": "Pemuco", "es_area": false, "peak_anio": 2002, "aun_creciente": false, "idx65_2024": 102.9, "idx65_2035": 172.3, "mapa_zonal": false}, {"id": "7107", "slug": "pencahue", "nombre": "Pencahue", "es_area": false, "peak_anio": 2024, "aun_creciente": false, "idx65_2024": 121.6, "idx65_2035": 203.0, "mapa_zonal": false}, {"id": "8107", "slug": "penco", "nombre": "Penco", "es_area": false, "peak_anio": 2031, "aun_creciente": false, "idx65_2024": 84.9, "idx65_2035": 140.4, "mapa_zonal": true}, {"id": "6307", "slug": "peralillo", "nombre": "Peralillo", "es_area": false, "peak_anio": 2035, "aun_creciente": true, "idx65_2024": 112.9, "idx65_2035": 193.4, "mapa_zonal": false}, {"id": "9113", "slug": "perquenco", "nombre": "Perquenco", "es_area": false, "peak_anio": 2028, "aun_creciente": false, "idx65_2024": 85.6, "idx65_2035": 139.7, "mapa_zonal": false}, {"id": "5404", "slug": "petorca", "nombre": "Petorca", "es_area": false, "peak_anio": 2029, "aun_creciente": false, "idx65_2024": 103.7, "idx65_2035": 162.1, "mapa_zonal": false}, {"id": "6112", "slug": "peumo", "nombre": "Peumo", "es_area": false, "peak_anio": 2029, "aun_creciente": false, "idx65_2024": 94.7, "idx65_2035": 159.2, "mapa_zonal": false}, {"id": "13605", "slug": "penaflor", "nombre": "Peñaflor", "es_area": false, "peak_anio": 2035, "aun_creciente": true, "idx65_2024": 56.7, "idx65_2035": 85.2, "mapa_zonal": true}, {"id": "13122", "slug": "penalolen", "nombre": "Peñalolén", "es_area": false, "peak_anio": 2035, "aun_creciente": true, "idx65_2024": 63.4, "idx65_2035": 94.6, "mapa_zonal": false}, {"id": "1405", "slug": "pica", "nombre": "Pica", "es_area": false, "peak_anio": 2035, "aun_creciente": true, "idx65_2024": 79.9, "idx65_2035": 130.8, "mapa_zonal": false}, {"id": "6113", "slug": "pichidegua", "nombre": "Pichidegua", "es_area": false, "peak_anio": 2033, "aun_creciente": false, "idx65_2024": 104.0, "idx65_2035": 175.3, "mapa_zonal": false}, {"id": "6201", "slug": "pichilemu", "nombre": "Pichilemu", "es_area": false, "peak_anio": 2035, "aun_creciente": true, "idx65_2024": 99.0, "idx65_2035": 167.7, "mapa_zonal": false}, {"id": "16106", "slug": "pinto", "nombre": "Pinto", "es_area": false, "peak_anio": 2035, "aun_creciente": true, "idx65_2024": 118.5, "idx65_2035": 195.5, "mapa_zonal": false}, {"id": "13202", "slug": "pirque", "nombre": "Pirque", "es_area": false, "peak_anio": 2035, "aun_creciente": true, "idx65_2024": 61.2, "idx65_2035": 92.1, "mapa_zonal": false}, {"id": "9114", "slug": "pitrufquen", "nombre": "Pitrufquén", "es_area": false, "peak_anio": 2035, "aun_creciente": true, "idx65_2024": 104.0, "idx65_2035": 170.0, "mapa_zonal": false}, {"id": "6308", "slug": "placilla", "nombre": "Placilla", "es_area": false, "peak_anio": 2035, "aun_creciente": true, "idx65_2024": 103.4, "idx65_2035": 175.3, "mapa_zonal": false}, {"id": "16205", "slug": "portezuelo", "nombre": "Portezuelo", "es_area": false, "peak_anio": 2002, "aun_creciente": false, "idx65_2024": 143.6, "idx65_2035": 241.9, "mapa_zonal": false}, {"id": "12301", "slug": "porvenir", "nombre": "Porvenir", "es_area": false, "peak_anio": 2035, "aun_creciente": true, "idx65_2024": 71.6, "idx65_2035": 106.5, "mapa_zonal": false}, {"id": "1401", "slug": "pozo_almonte", "nombre": "Pozo Almonte", "es_area": false, "peak_anio": 2035, "aun_creciente": true, "idx65_2024": 41.9, "idx65_2035": 67.7, "mapa_zonal": false}, {"id": "12302", "slug": "primavera", "nombre": "Primavera", "es_area": false, "peak_anio": 2002, "aun_creciente": false, "idx65_2024": 60.0, "idx65_2035": 75.9, "mapa_zonal": false}, {"id": "13123", "slug": "providencia", "nombre": "Providencia", "es_area": false, "peak_anio": 2035, "aun_creciente": true, "idx65_2024": 151.1, "idx65_2035": 235.2, "mapa_zonal": false}, {"id": "5105", "slug": "puchuncavi", "nombre": "Puchuncaví", "es_area": false, "peak_anio": 2035, "aun_creciente": true, "idx65_2024": 96.1, "idx65_2035": 149.5, "mapa_zonal": true}, {"id": "9115", "slug": "pucon", "nombre": "Pucón", "es_area": false, "peak_anio": 2035, "aun_creciente": true, "idx65_2024": 66.7, "idx65_2035": 108.0, "mapa_zonal": false}, {"id": "13124", "slug": "pudahuel", "nombre": "Pudahuel", "es_area": false, "peak_anio": 2035, "aun_creciente": true, "idx65_2024": 50.9, "idx65_2035": 75.8, "mapa_zonal": false}, {"id": "13201", "slug": "puente_alto", "nombre": "Puente Alto", "es_area": false, "peak_anio": 2034, "aun_creciente": false, "idx65_2024": 44.7, "idx65_2035": 66.1, "mapa_zonal": false}, {"id": "10101", "slug": "puerto_montt", "nombre": "Puerto Montt", "es_area": false, "peak_anio": 2035, "aun_creciente": true, "idx65_2024": 56.1, "idx65_2035": 97.1, "mapa_zonal": false}, {"id": "10302", "slug": "puerto_octay", "nombre": "Puerto Octay", "es_area": false, "peak_anio": 2002, "aun_creciente": false, "idx65_2024": 93.9, "idx65_2035": 163.5, "mapa_zonal": false}, {"id": "10109", "slug": "puerto_varas", "nombre": "Puerto Varas", "es_area": false, "peak_anio": 2035, "aun_creciente": true, "idx65_2024": 63.4, "idx65_2035": 109.7, "mapa_zonal": false}, {"id": "6309", "slug": "pumanque", "nombre": "Pumanque", "es_area": false, "peak_anio": 2002, "aun_creciente": false, "idx65_2024": 208.4, "idx65_2035": 354.2, "mapa_zonal": false}, {"id": "4304", "slug": "punitaqui", "nombre": "Punitaqui", "es_area": false, "peak_anio": 2035, "aun_creciente": true, "idx65_2024": 93.0, "idx65_2035": 154.4, "mapa_zonal": false}, {"id": "12101", "slug": "punta_arenas", "nombre": "Punta Arenas", "es_area": false, "peak_anio": 2035, "aun_creciente": true, "idx65_2024": 84.5, "idx65_2035": 126.4, "mapa_zonal": true}, {"id": "10206", "slug": "puqueldon", "nombre": "Puqueldón", "es_area": false, "peak_anio": 2002, "aun_creciente": false, "idx65_2024": 132.5, "idx65_2035": 230.1, "mapa_zonal": false}, {"id": "10303", "slug": "purranque", "nombre": "Purranque", "es_area": false, "peak_anio": 2002, "aun_creciente": false, "idx65_2024": 109.6, "idx65_2035": 192.3, "mapa_zonal": false}, {"id": "9208", "slug": "puren", "nombre": "Purén", "es_area": false, "peak_anio": 2002, "aun_creciente": false, "idx65_2024": 97.4, "idx65_2035": 160.0, "mapa_zonal": false}, {"id": "5705", "slug": "putaendo", "nombre": "Putaendo", "es_area": false, "peak_anio": 2035, "aun_creciente": true, "idx65_2024": 100.0, "idx65_2035": 157.7, "mapa_zonal": false}, {"id": "15201", "slug": "putre", "nombre": "Putre", "es_area": false, "peak_anio": 2035, "aun_creciente": true, "idx65_2024": 120.3, "idx65_2035": 196.3, "mapa_zonal": false}, {"id": "10304", "slug": "puyehue", "nombre": "Puyehue", "es_area": false, "peak_anio": 2030, "aun_creciente": false, "idx65_2024": 107.6, "idx65_2035": 188.7, "mapa_zonal": false}, {"id": "10207", "slug": "queilen", "nombre": "Queilén", "es_area": false, "peak_anio": 2021, "aun_creciente": false, "idx65_2024": 94.3, "idx65_2035": 166.2, "mapa_zonal": false}, {"id": "10208", "slug": "quellon", "nombre": "Quellón", "es_area": false, "peak_anio": 2035, "aun_creciente": true, "idx65_2024": 45.3, "idx65_2035": 78.5, "mapa_zonal": false}, {"id": "10209", "slug": "quemchi", "nombre": "Quemchi", "es_area": false, "peak_anio": 2002, "aun_creciente": false, "idx65_2024": 118.1, "idx65_2035": 209.4, "mapa_zonal": false}, {"id": "8308", "slug": "quilaco", "nombre": "Quilaco", "es_area": false, "peak_anio": 2022, "aun_creciente": false, "idx65_2024": 161.1, "idx65_2035": 271.0, "mapa_zonal": false}, {"id": "13125", "slug": "quilicura", "nombre": "Quilicura", "es_area": false, "peak_anio": 2035, "aun_creciente": true, "idx65_2024": 30.1, "idx65_2035": 44.1, "mapa_zonal": false}, {"id": "8309", "slug": "quilleco", "nombre": "Quilleco", "es_area": false, "peak_anio": 2002, "aun_creciente": false, "idx65_2024": 129.7, "idx65_2035": 220.2, "mapa_zonal": false}, {"id": "5501", "slug": "quillota", "nombre": "Quillota", "es_area": false, "peak_anio": 2035, "aun_creciente": true, "idx65_2024": 88.0, "idx65_2035": 137.3, "mapa_zonal": true}, {"id": "16107", "slug": "quillon", "nombre": "Quillón", "es_area": false, "peak_anio": 2035, "aun_creciente": true, "idx65_2024": 136.5, "idx65_2035": 226.7, "mapa_zonal": false}, {"id": "5801", "slug": "quilpue", "nombre": "Quilpué", "es_area": false, "peak_anio": 2035, "aun_creciente": true, "idx65_2024": 105.9, "idx65_2035": 165.9, "mapa_zonal": false}, {"id": "10210", "slug": "quinchao", "nombre": "Quinchao", "es_area": false, "peak_anio": 2002, "aun_creciente": false, "idx65_2024": 111.4, "idx65_2035": 195.7, "mapa_zonal": false}, {"id": "6114", "slug": "quinta_de_tilcoco", "nombre": "Quinta De Tilcoco", "es_area": false, "peak_anio": 2035, "aun_creciente": true, "idx65_2024": 95.1, "idx65_2035": 159.6, "mapa_zonal": false}, {"id": "13126", "slug": "quinta_normal", "nombre": "Quinta Normal", "es_area": false, "peak_anio": 2035, "aun_creciente": true, "idx65_2024": 92.5, "idx65_2035": 141.0, "mapa_zonal": false}, {"id": "5107", "slug": "quintero", "nombre": "Quintero", "es_area": false, "peak_anio": 2035, "aun_creciente": true, "idx65_2024": 85.6, "idx65_2035": 133.1, "mapa_zonal": true}, {"id": "16201", "slug": "quirihue", "nombre": "Quirihue", "es_area": false, "peak_anio": 2026, "aun_creciente": false, "idx65_2024": 121.4, "idx65_2035": 202.3, "mapa_zonal": false}, {"id": "6101", "slug": "rancagua", "nombre": "Rancagua", "es_area": false, "peak_anio": 2035, "aun_creciente": true, "idx65_2024": 78.0, "idx65_2035": 130.5, "mapa_zonal": false}, {"id": "7305", "slug": "rauco", "nombre": "Rauco", "es_area": false, "peak_anio": 2035, "aun_creciente": true, "idx65_2024": 98.4, "idx65_2035": 162.3, "mapa_zonal": false}, {"id": "13127", "slug": "recoleta", "nombre": "Recoleta", "es_area": false, "peak_anio": 2035, "aun_creciente": true, "idx65_2024": 87.5, "idx65_2035": 132.4, "mapa_zonal": false}, {"id": "9209", "slug": "renaico", "nombre": "Renaico", "es_area": false, "peak_anio": 2035, "aun_creciente": true, "idx65_2024": 79.0, "idx65_2035": 127.2, "mapa_zonal": false}, {"id": "13128", "slug": "renca", "nombre": "Renca", "es_area": false, "peak_anio": 2035, "aun_creciente": true, "idx65_2024": 58.2, "idx65_2035": 86.7, "mapa_zonal": false}, {"id": "6115", "slug": "rengo", "nombre": "Rengo", "es_area": false, "peak_anio": 2035, "aun_creciente": true, "idx65_2024": 78.5, "idx65_2035": 132.0, "mapa_zonal": true}, {"id": "6116", "slug": "requinoa", "nombre": "Requínoa", "es_area": false, "peak_anio": 2035, "aun_creciente": true, "idx65_2024": 65.4, "idx65_2035": 109.3, "mapa_zonal": false}, {"id": "7405", "slug": "retiro", "nombre": "Retiro", "es_area": false, "peak_anio": 2035, "aun_creciente": true, "idx65_2024": 99.5, "idx65_2035": 163.1, "mapa_zonal": false}, {"id": "5303", "slug": "rinconada", "nombre": "Rinconada", "es_area": false, "peak_anio": 2035, "aun_creciente": true, "idx65_2024": 62.6, "idx65_2035": 97.0, "mapa_zonal": false}, {"id": "7306", "slug": "romeral", "nombre": "Romeral", "es_area": false, "peak_anio": 2035, "aun_creciente": true, "idx65_2024": 80.7, "idx65_2035": 132.0, "mapa_zonal": false}, {"id": "16206", "slug": "ranquil", "nombre": "Ránquil", "es_area": false, "peak_anio": 2025, "aun_creciente": false, "idx65_2024": 153.6, "idx65_2035": 257.3, "mapa_zonal": false}, {"id": "14204", "slug": "rio_bueno", "nombre": "Río Bueno", "es_area": false, "peak_anio": 2002, "aun_creciente": false, "idx65_2024": 106.7, "idx65_2035": 173.9, "mapa_zonal": false}, {"id": "7108", "slug": "rio_claro", "nombre": "Río Claro", "es_area": false, "peak_anio": 2035, "aun_creciente": true, "idx65_2024": 97.0, "idx65_2035": 157.9, "mapa_zonal": false}, {"id": "4305", "slug": "rio_hurtado", "nombre": "Río Hurtado", "es_area": false, "peak_anio": 2002, "aun_creciente": false, "idx65_2024": 157.1, "idx65_2035": 266.3, "mapa_zonal": false}, {"id": "11402", "slug": "rio_ibanez", "nombre": "Río Ibáñez", "es_area": false, "peak_anio": 2027, "aun_creciente": false, "idx65_2024": 150.0, "idx65_2035": 254.1, "mapa_zonal": false}, {"id": "10305", "slug": "rio_negro", "nombre": "Río Negro", "es_area": false, "peak_anio": 2002, "aun_creciente": false, "idx65_2024": 120.7, "idx65_2035": 211.6, "mapa_zonal": false}, {"id": "12103", "slug": "rio_verde", "nombre": "Río Verde", "es_area": false, "peak_anio": 2002, "aun_creciente": false, "idx65_2024": 300.0, "idx65_2035": 300.0, "mapa_zonal": false}, {"id": "9116", "slug": "saavedra", "nombre": "Saavedra", "es_area": false, "peak_anio": 2002, "aun_creciente": false, "idx65_2024": 102.6, "idx65_2035": 168.6, "mapa_zonal": false}, {"id": "7307", "slug": "sagrada_familia", "nombre": "Sagrada Familia", "es_area": false, "peak_anio": 2035, "aun_creciente": true, "idx65_2024": 92.0, "idx65_2035": 150.6, "mapa_zonal": false}, {"id": "4204", "slug": "salamanca", "nombre": "Salamanca", "es_area": false, "peak_anio": 2035, "aun_creciente": true, "idx65_2024": 88.0, "idx65_2035": 146.1, "mapa_zonal": false}, {"id": "5601", "slug": "san_antonio", "nombre": "San Antonio", "es_area": false, "peak_anio": 2035, "aun_creciente": true, "idx65_2024": 83.1, "idx65_2035": 128.7, "mapa_zonal": true}, {"id": "13401", "slug": "san_bernardo", "nombre": "San Bernardo", "es_area": false, "peak_anio": 2035, "aun_creciente": true, "idx65_2024": 48.4, "idx65_2035": 72.2, "mapa_zonal": false}, {"id": "16301", "slug": "san_carlos", "nombre": "San Carlos", "es_area": false, "peak_anio": 2035, "aun_creciente": true, "idx65_2024": 104.5, "idx65_2035": 173.6, "mapa_zonal": true}, {"id": "7109", "slug": "san_clemente", "nombre": "San Clemente", "es_area": false, "peak_anio": 2035, "aun_creciente": true, "idx65_2024": 82.5, "idx65_2035": 134.5, "mapa_zonal": false}, {"id": "5304", "slug": "san_esteban", "nombre": "San Esteban", "es_area": false, "peak_anio": 2035, "aun_creciente": true, "idx65_2024": 72.9, "idx65_2035": 113.2, "mapa_zonal": false}, {"id": "16304", "slug": "san_fabian", "nombre": "San Fabián", "es_area": false, "peak_anio": 2035, "aun_creciente": true, "idx65_2024": 127.4, "idx65_2035": 214.3, "mapa_zonal": false}, {"id": "5701", "slug": "san_felipe", "nombre": "San Felipe", "es_area": false, "peak_anio": 2035, "aun_creciente": true, "idx65_2024": 72.5, "idx65_2035": 112.5, "mapa_zonal": true}, {"id": "6301", "slug": "san_fernando", "nombre": "San Fernando", "es_area": false, "peak_anio": 2035, "aun_creciente": true, "idx65_2024": 79.9, "idx65_2035": 134.8, "mapa_zonal": true}, {"id": "12104", "slug": "san_gregorio", "nombre": "San Gregorio", "es_area": false, "peak_anio": 2002, "aun_creciente": false, "idx65_2024": 70.1, "idx65_2035": 90.8, "mapa_zonal": false}, {"id": "16108", "slug": "san_ignacio", "nombre": "San Ignacio", "es_area": false, "peak_anio": 2002, "aun_creciente": false, "idx65_2024": 114.4, "idx65_2035": 190.4, "mapa_zonal": false}, {"id": "7406", "slug": "san_javier", "nombre": "San Javier", "es_area": false, "peak_anio": 2035, "aun_creciente": true, "idx65_2024": 88.3, "idx65_2035": 145.8, "mapa_zonal": true}, {"id": "13129", "slug": "san_joaquin", "nombre": "San Joaquín", "es_area": false, "peak_anio": 2002, "aun_creciente": false, "idx65_2024": 107.9, "idx65_2035": 165.0, "mapa_zonal": false}, {"id": "13203", "slug": "san_jose_de_maipo", "nombre": "San José De Maipo", "es_area": false, "peak_anio": 2035, "aun_creciente": true, "idx65_2024": 76.2, "idx65_2035": 115.3, "mapa_zonal": false}, {"id": "10306", "slug": "san_juan_de_la_costa", "nombre": "San Juan De La Costa", "es_area": false, "peak_anio": 2002, "aun_creciente": false, "idx65_2024": 156.4, "idx65_2035": 276.9, "mapa_zonal": false}, {"id": "13130", "slug": "san_miguel", "nombre": "San Miguel", "es_area": false, "peak_anio": 2035, "aun_creciente": true, "idx65_2024": 94.1, "idx65_2035": 144.5, "mapa_zonal": false}, {"id": "16305", "slug": "san_nicolas", "nombre": "San Nicolás", "es_area": false, "peak_anio": 2035, "aun_creciente": true, "idx65_2024": 112.8, "idx65_2035": 185.6, "mapa_zonal": false}, {"id": "10307", "slug": "san_pablo", "nombre": "San Pablo", "es_area": false, "peak_anio": 2021, "aun_creciente": false, "idx65_2024": 133.3, "idx65_2035": 233.7, "mapa_zonal": false}, {"id": "13505", "slug": "san_pedro", "nombre": "San Pedro", "es_area": false, "peak_anio": 2035, "aun_creciente": true, "idx65_2024": 84.9, "idx65_2035": 129.9, "mapa_zonal": false}, {"id": "2203", "slug": "san_pedro_de_atacama", "nombre": "San Pedro De Atacama", "es_area": false, "peak_anio": 2035, "aun_creciente": true, "idx65_2024": 44.3, "idx65_2035": 70.6, "mapa_zonal": false}, {"id": "8108", "slug": "san_pedro_de_la_paz", "nombre": "San Pedro De La Paz", "es_area": false, "peak_anio": 2035, "aun_creciente": true, "idx65_2024": 54.1, "idx65_2035": 89.2, "mapa_zonal": true}, {"id": "7110", "slug": "san_rafael", "nombre": "San Rafael", "es_area": false, "peak_anio": 2035, "aun_creciente": true, "idx65_2024": 81.8, "idx65_2035": 132.4, "mapa_zonal": false}, {"id": "13131", "slug": "san_ramon", "nombre": "San Ramón", "es_area": false, "peak_anio": 2002, "aun_creciente": false, "idx65_2024": 96.2, "idx65_2035": 146.0, "mapa_zonal": false}, {"id": "8310", "slug": "san_rosendo", "nombre": "San Rosendo", "es_area": false, "peak_anio": 2002, "aun_creciente": false, "idx65_2024": 122.2, "idx65_2035": 205.5, "mapa_zonal": false}, {"id": "6117", "slug": "san_vicente", "nombre": "San Vicente", "es_area": false, "peak_anio": 2035, "aun_creciente": true, "idx65_2024": 99.2, "idx65_2035": 168.5, "mapa_zonal": true}, {"id": "8311", "slug": "santa_barbara", "nombre": "Santa Bárbara", "es_area": false, "peak_anio": 2030, "aun_creciente": false, "idx65_2024": 91.9, "idx65_2035": 155.4, "mapa_zonal": false}, {"id": "6310", "slug": "santa_cruz", "nombre": "Santa Cruz", "es_area": false, "peak_anio": 2035, "aun_creciente": true, "idx65_2024": 93.9, "idx65_2035": 159.2, "mapa_zonal": false}, {"id": "8109", "slug": "santa_juana", "nombre": "Santa Juana", "es_area": false, "peak_anio": 2029, "aun_creciente": false, "idx65_2024": 102.8, "idx65_2035": 173.4, "mapa_zonal": false}, {"id": "5706", "slug": "santa_maria", "nombre": "Santa María", "es_area": false, "peak_anio": 2035, "aun_creciente": true, "idx65_2024": 80.2, "idx65_2035": 124.3, "mapa_zonal": false}, {"id": "13101", "slug": "santiago", "nombre": "Santiago", "es_area": false, "peak_anio": 2035, "aun_creciente": true, "idx65_2024": 79.5, "idx65_2035": 120.9, "mapa_zonal": false}, {"id": "5606", "slug": "santo_domingo", "nombre": "Santo Domingo", "es_area": false, "peak_anio": 2035, "aun_creciente": true, "idx65_2024": 86.4, "idx65_2035": 134.2, "mapa_zonal": false}, {"id": "2103", "slug": "sierra_gorda", "nombre": "Sierra Gorda", "es_area": false, "peak_anio": 2035, "aun_creciente": true, "idx65_2024": 30.2, "idx65_2035": 47.1, "mapa_zonal": false}, {"id": "13601", "slug": "talagante", "nombre": "Talagante", "es_area": false, "peak_anio": 2035, "aun_creciente": true, "idx65_2024": 56.0, "idx65_2035": 84.3, "mapa_zonal": true}, {"id": "7101", "slug": "talca", "nombre": "Talca", "es_area": false, "peak_anio": 2035, "aun_creciente": true, "idx65_2024": 87.7, "idx65_2035": 143.6, "mapa_zonal": true}, {"id": "8110", "slug": "talcahuano", "nombre": "Talcahuano", "es_area": false, "peak_anio": 2002, "aun_creciente": false, "idx65_2024": 91.5, "idx65_2035": 152.8, "mapa_zonal": true}, {"id": "2104", "slug": "taltal", "nombre": "Taltal", "es_area": false, "peak_anio": 2032, "aun_creciente": false, "idx65_2024": 52.0, "idx65_2035": 82.3, "mapa_zonal": false}, {"id": "9101", "slug": "temuco", "nombre": "Temuco", "es_area": false, "peak_anio": 2035, "aun_creciente": true, "idx65_2024": 74.4, "idx65_2035": 120.0, "mapa_zonal": false}, {"id": "7308", "slug": "teno", "nombre": "Teno", "es_area": false, "peak_anio": 2035, "aun_creciente": true, "idx65_2024": 88.0, "idx65_2035": 144.4, "mapa_zonal": false}, {"id": "9117", "slug": "teodoro_schmidt", "nombre": "Teodoro Schmidt", "es_area": false, "peak_anio": 2002, "aun_creciente": false, "idx65_2024": 114.5, "idx65_2035": 186.8, "mapa_zonal": false}, {"id": "3103", "slug": "tierra_amarilla", "nombre": "Tierra Amarilla", "es_area": false, "peak_anio": 2028, "aun_creciente": false, "idx65_2024": 47.0, "idx65_2035": 77.7, "mapa_zonal": false}, {"id": "13303", "slug": "tiltil", "nombre": "Tiltil", "es_area": false, "peak_anio": 2035, "aun_creciente": true, "idx65_2024": 61.0, "idx65_2035": 91.8, "mapa_zonal": false}, {"id": "12303", "slug": "timaukel", "nombre": "Timaukel", "es_area": false, "peak_anio": 2002, "aun_creciente": false, "idx65_2024": 60.0, "idx65_2035": 75.0, "mapa_zonal": false}, {"id": "8207", "slug": "tirua", "nombre": "Tirúa", "es_area": false, "peak_anio": 2031, "aun_creciente": false, "idx65_2024": 56.5, "idx65_2035": 94.2, "mapa_zonal": false}, {"id": "2301", "slug": "tocopilla", "nombre": "Tocopilla", "es_area": false, "peak_anio": 2031, "aun_creciente": false, "idx65_2024": 56.8, "idx65_2035": 88.3, "mapa_zonal": false}, {"id": "9118", "slug": "tolten", "nombre": "Toltén", "es_area": false, "peak_anio": 2002, "aun_creciente": false, "idx65_2024": 104.6, "idx65_2035": 172.3, "mapa_zonal": false}, {"id": "8111", "slug": "tome", "nombre": "Tomé", "es_area": false, "peak_anio": 2030, "aun_creciente": false, "idx65_2024": 106.6, "idx65_2035": 179.1, "mapa_zonal": true}, {"id": "12402", "slug": "torres_del_paine", "nombre": "Torres Del Paine", "es_area": false, "peak_anio": 2035, "aun_creciente": true, "idx65_2024": 122.4, "idx65_2035": 175.8, "mapa_zonal": false}, {"id": "11303", "slug": "tortel", "nombre": "Tortel", "es_area": false, "peak_anio": 2034, "aun_creciente": false, "idx65_2024": 47.6, "idx65_2035": 74.1, "mapa_zonal": false}, {"id": "9210", "slug": "traiguen", "nombre": "Traiguén", "es_area": false, "peak_anio": 2002, "aun_creciente": false, "idx65_2024": 104.3, "idx65_2035": 170.3, "mapa_zonal": false}, {"id": "16207", "slug": "trehuaco", "nombre": "Trehuaco", "es_area": false, "peak_anio": 2034, "aun_creciente": false, "idx65_2024": 128.5, "idx65_2035": 214.2, "mapa_zonal": false}, {"id": "8312", "slug": "tucapel", "nombre": "Tucapel", "es_area": false, "peak_anio": 2035, "aun_creciente": true, "idx65_2024": 109.2, "idx65_2035": 185.0, "mapa_zonal": false}, {"id": "14101", "slug": "valdivia", "nombre": "Valdivia", "es_area": false, "peak_anio": 2035, "aun_creciente": true, "idx65_2024": 83.2, "idx65_2035": 134.4, "mapa_zonal": true}, {"id": "3301", "slug": "vallenar", "nombre": "Vallenar", "es_area": false, "peak_anio": 2025, "aun_creciente": false, "idx65_2024": 72.7, "idx65_2035": 122.6, "mapa_zonal": true}, {"id": "5101", "slug": "valparaiso", "nombre": "Valparaíso", "es_area": false, "peak_anio": 2035, "aun_creciente": true, "idx65_2024": 100.4, "idx65_2035": 156.2, "mapa_zonal": false}, {"id": "7309", "slug": "vichuquen", "nombre": "Vichuquén", "es_area": false, "peak_anio": 2002, "aun_creciente": false, "idx65_2024": 139.0, "idx65_2035": 229.4, "mapa_zonal": false}, {"id": "9211", "slug": "victoria", "nombre": "Victoria", "es_area": false, "peak_anio": 2025, "aun_creciente": false, "idx65_2024": 96.5, "idx65_2035": 156.4, "mapa_zonal": false}, {"id": "4106", "slug": "vicuna", "nombre": "Vicuña", "es_area": false, "peak_anio": 2035, "aun_creciente": true, "idx65_2024": 79.2, "idx65_2035": 131.8, "mapa_zonal": false}, {"id": "9119", "slug": "vilcun", "nombre": "Vilcún", "es_area": false, "peak_anio": 2035, "aun_creciente": true, "idx65_2024": 69.6, "idx65_2035": 112.8, "mapa_zonal": false}, {"id": "7407", "slug": "villa_alegre", "nombre": "Villa Alegre", "es_area": false, "peak_anio": 2035, "aun_creciente": true, "idx65_2024": 104.7, "idx65_2035": 172.7, "mapa_zonal": false}, {"id": "5804", "slug": "villa_alemana", "nombre": "Villa Alemana", "es_area": false, "peak_anio": 2035, "aun_creciente": true, "idx65_2024": 86.7, "idx65_2035": 135.4, "mapa_zonal": false}, {"id": "9120", "slug": "villarrica", "nombre": "Villarrica", "es_area": false, "peak_anio": 2035, "aun_creciente": true, "idx65_2024": 76.0, "idx65_2035": 122.9, "mapa_zonal": true}, {"id": "13132", "slug": "vitacura", "nombre": "Vitacura", "es_area": false, "peak_anio": 2021, "aun_creciente": false, "idx65_2024": 120.1, "idx65_2035": 185.3, "mapa_zonal": false}, {"id": "5109", "slug": "vina_del_mar", "nombre": "Viña Del Mar", "es_area": false, "peak_anio": 2033, "aun_creciente": false, "idx65_2024": 118.7, "idx65_2035": 186.9, "mapa_zonal": false}, {"id": "7408", "slug": "yerbas_buenas", "nombre": "Yerbas Buenas", "es_area": false, "peak_anio": 2035, "aun_creciente": true, "idx65_2024": 82.3, "idx65_2035": 133.1, "mapa_zonal": false}, {"id": "8313", "slug": "yumbel", "nombre": "Yumbel", "es_area": false, "peak_anio": 2029, "aun_creciente": false, "idx65_2024": 132.1, "idx65_2035": 224.0, "mapa_zonal": false}, {"id": "16109", "slug": "yungay", "nombre": "Yungay", "es_area": false, "peak_anio": 2035, "aun_creciente": true, "idx65_2024": 109.2, "idx65_2035": 183.4, "mapa_zonal": false}, {"id": "5405", "slug": "zapallar", "nombre": "Zapallar", "es_area": false, "peak_anio": 2035, "aun_creciente": true, "idx65_2024": 102.6, "idx65_2035": 158.9, "mapa_zonal": false}, {"id": "16303", "slug": "niquen", "nombre": "Ñiquén", "es_area": false, "peak_anio": 2002, "aun_creciente": false, "idx65_2024": 144.2, "idx65_2035": 239.5, "mapa_zonal": false}, {"id": "13120", "slug": "nunoa", "nombre": "Ñuñoa", "es_area": false, "peak_anio": 2035, "aun_creciente": true, "idx65_2024": 120.3, "idx65_2035": 185.6, "mapa_zonal": false}], "def_indice": "Índice de envejecimiento = personas de 65+ por cada 100 menores de 15 años.", "nota": "INE Estimaciones y Proyecciones 2002-2035 por comuna. Mapa por zona: Censo 2024 (tramos 60+/0-13), proyección escalada por comuna. Provisional."}